Workbook

Sheet Single Tool
A1: Single Store Policy HTML Generator
A2: Store Name
A3: Support Email
A4: Website Domain (optional)
A5: Mailing Address (optional)
A6: Last Updated | B6: March 12, 2026
A8: Refund, Replacement & Cancellation Policy HTML
A9: Output | B9: =SUBSTITUTE(SUBSTITUTE(Templates!$B$2,"{{STORE}}",$B$2),"{{EMAIL}}",$B$3) -> <h4 style="text-align: center;">Refund, Replacement &amp; Cancellation Policy</h4> <p>At , each product is made to order and produced specifically for you after the order is placed. Because of this, we maintain a strict but fair refund and replacement policy.</p> <p><strong>1. Order Cancellation</strong></p> <p>Orders may be cancelled <strong>within 6 hours of placing the order.</strong><br>After this period, the order may already be in production and cannot be cancelled or modified.<br>To request a cancellation, please contact us immediately at: </p> <p>Requests submitted after the 6-hour cancellation window cannot be guaranteed as the order may already be in production.</p> <p>If a cancellation request is approved within the allowed time window, a 30% management, processing, and transaction fee will be deducted from the total order value.<br>This fee covers costs that are non-recoverable once the order is placed, including but not limited to:<br>- Payment processing and transaction fees<br>- Order processing and administrative costs<br>- Production preparation and fulfillment system allocation<br>The remaining balance will be refunded to the original payment method.</p> <p><strong>2. Defective, Damaged, or Incorrect Items</strong></p> <p>If you receive an item that is <strong>defective, damaged during shipping, or incorrect</strong>, please contact us within <strong>72 hours after delivery confirmation.</strong><br>Your email must include:<br>- Your order number<br>- <strong>Clear photos</strong> of the product and the issue<br>- A brief description of the problem</p> <p>Please send your request to: </p> <p>After review and approval, we will <strong>either</strong>:<br>- Send a <strong>free replacement</strong>, or<br>- Issue a <strong>full refund</strong></p> <p>We may request additional photos or information to verify the issue.<br>In some cases, we may request the defective item to be returned before processing the resolution.</p> <p><strong>3. Custom &amp; Made-To-Order Products</strong></p> <p>All products sold on are <strong>custom-made or printed on demand.</strong><br>Because these products are made specifically for each order, <strong>we do not accept returns or refunds for the following reasons:</strong><br>- Incorrect size ordered<br>- Change of mind<br>- Incorrect shipping address provided by the customer<br>- Minor color differences due to screen display<br>- Custom name or personalization errors provided by the customer</p> <p>However, we understand mistakes happen. As a courtesy, we may offer <strong>a replacement with a 50% discount</strong> if you wish to reorder the correct size, color, or product.</p> <p><strong>4. Refund Processing</strong></p> <p>If your refund request is approved, refunds will be processed to your <strong>original payment method.</strong><br>Please allow <strong>5–7 business days</strong> for the refund to appear in your account depending on your bank or payment provider.<br>Once a refund has been issued, we will send a <strong>confirmation email.</strong></p> <p><strong>5. Late or Missing Refunds</strong></p> <p>If you have not received your refund:<br>- Check your bank account again.<br>- Contact your credit card company or payment provider.<br>- Contact your bank.</p> <p>Refunds can take several business days to process depending on your financial institution.<br>If 10 business days have passed since the refund confirmation and you still have not received the funds, please contact us at: </p> <p><strong>6. Chargebacks &amp; Payment Disputes</strong></p> <p>If a chargeback or payment dispute is opened without contacting our support team first, we reserve the right to submit all order information, delivery confirmation, and communication records to the payment provider.<br>We are always happy to resolve any issues directly with our customers and encourage contacting us first for the fastest resolution.</p>
A11: Production & Shipping Policy HTML
A12: Output | B12: =SUBSTITUTE(SUBSTITUTE(Templates!$B$3,"{{STORE}}",$B$2),"{{EMAIL}}",$B$3) -> <p><strong>Production Time</strong></p> <p>All products at are made-to-order and produced specifically according to your selected design, size, and color. We do not keep inventory, which means each item is manufactured after your order is placed.<br>Production typically takes 5–10 business days (excluding weekends and holidays) before the order is shipped.<br>Orders enter the production process within 6 hours after being placed. Once production has started, orders cannot be modified or canceled.</p> <p><strong>Shipping Time</strong></p> <p>After production is completed, your order will be shipped according to the shipping method selected at checkout.</p> <p>Estimated delivery times:<br>Standard Shipping: 10–20 business days<br>Fast Shipping: 5–10 business days</p> <p>Delivery times may vary depending on your location, customs processing, and carrier delays.<br>Once your order has been shipped, you will receive a tracking number via email.</p> <p><strong>Estimated Delivery Time</strong></p> <p>Total estimated delivery time includes production time + shipping time.<br>Example:<br>- Standard Shipping: 15–30 business days total<br>- Fast Shipping: 10–20 business days total</p> <p>For the most accurate estimate, please check the estimated delivery date on your order confirmation email.<br>If you have any questions about your order, please contact us at: </p> <p><strong>Shipping Cost</strong></p> <p>- $5.95 for orders under $90<br>- Free shipping for orders $90 and above</p> <p><strong> is not responsible for delays caused by carriers, customs clearance, weather conditions, or peak holiday seasons.</strong></p>
A14: Terms of Service HTML
A15: Output | B15: =SUBSTITUTE(SUBSTITUTE(SUBSTITUTE(SUBSTITUTE(SUBSTITUTE(Templates!$B$4,"{{STORE}}",$B$2),"{{EMAIL}}",$B$3),"{{DOMAIN}}",IF(B4<>"",B4,IFERROR(MID(B3,FIND("@",B3)+1,255),""))),"{{LAST_UPDATED}}",$B$6),"{{ADDRESS_TEXT}}",IF(B5<>"",B5,"[Add mailing address]")) -> <p><strong>OVERVIEW</strong><br> Welcome to ! The terms “we”, “us” and “our” refer to . operates this store and website, including all related information, content, features, tools, products and services in order to provide you with a shopping experience. is powered by Shopify. </p> <p>By visiting or using our Services, you agree to these Terms of Service.</p> <p><strong>SECTION 1 - ACCESS</strong><br> You must be at least the age of majority in your jurisdiction to use this website. </p> <p><strong>SECTION 2 - PRODUCTS</strong><br> Product colors may appear differently depending on your device display. </p> <p><strong>SECTION 3 - ORDERS</strong><br> We reserve the right to refuse or cancel orders at our discretion. </p> <p><strong>SECTION 4 - PRICES</strong><br> Prices may change without notice. </p> <p><strong>SECTION 5 - SHIPPING</strong><br> Delivery times are estimates only. </p> <p><strong>SECTION 6 - INTELLECTUAL PROPERTY</strong><br> All website content belongs to or its licensors. </p> <p><strong>SECTION 7 - THIRD PARTY LINKS</strong><br> We are not responsible for third‑party websites linked from our store. </p> <p><strong>SECTION 8 - LIABILITY</strong><br> is not liable for damages resulting from the use of this website. </p> <p><strong>SECTION 9 - CONTACT</strong><br> Questions about the Terms of Service should be sent to:<br> </p> <hr>
A17: Privacy Policy HTML
A18: Output | B18: =SUBSTITUTE(SUBSTITUTE(SUBSTITUTE(SUBSTITUTE(SUBSTITUTE(Templates!$B$5,"{{STORE}}",$B$2),"{{EMAIL}}",$B$3),"{{DOMAIN}}",IF(B4<>"",B4,IFERROR(MID(B3,FIND("@",B3)+1,255),""))),"{{LAST_UPDATED}}",$B$6),"{{ADDRESS_TEXT}}",IF(B5<>"",B5,"[Add mailing address]")) -> <p><strong>Last updated:</strong> March 12, 2026</p> <p> operates this website and collects certain personal information to provide services. </p> <h2>Information We Collect</h2> <ul> <li>Name</li> <li>Email</li> <li>Shipping address</li> <li>Billing address</li> <li>Payment details</li> <li>Device information</li> </ul> <h2>How We Use Information</h2> <ul> <li>Process orders</li> <li>Provide support</li> <li>Improve the store</li> <li>Prevent fraud</li> </ul> <h2>Sharing Information</h2> <p> We may share information with Shopify, payment providers, and shipping partners to fulfill orders. </p> <h2>Cookies</h2> <p> Cookies are used to improve user experience and analyze website traffic. </p> <h2>Your Rights</h2> <p> You may request access, correction, or deletion of your personal information. </p> <h2>Security</h2> <p> We implement security measures to protect your data but cannot guarantee absolute security. </p> <h2>Contact</h2> <p> For privacy questions contact:<br> </p>

Sheet Batch Generator
A1: Batch Policy HTML Generator
A2: Store Name | B2: Support Email | C2: Website Domain (optional) | D2: Mailing Address (optional) | E2: Last Updated | F2: Refund HTML | G2: Shipping HTML | H2: Terms HTML | I2: Privacy HTML
A3: WanderWild | B3: contact@podcrewshop.com | E3: March 12, 2026 | F3: =SUBSTITUTE(SUBSTITUTE(Templates!$B$2,"{{STORE}}",$A3),"{{EMAIL}}",$B3) -> <h4 style="text-align: center;">Refund, Replacement &amp; Cancellation Policy</h4> <p>At WanderWild, each product is made to order and produced specifically for you after the order is placed. Because of this, we maintain a strict but fair refund and replacement policy.</p> <p><strong>1. Order Cancellation</strong></p> <p>Orders may be cancelled <strong>within 6 hours of placing the order.</strong><br>After this period, the order may already be in production and cannot be cancelled or modified.<br>To request a cancellation, please contact us immediately at: contact@podcrewshop.com</p> <p>Requests submitted after the 6-hour cancellation window cannot be guaranteed as the order may already be in production.</p> <p>If a cancellation request is approved within the allowed time window, a 30% management, processing, and transaction fee will be deducted from the total order value.<br>This fee covers costs that are non-recoverable once the order is placed, including but not limited to:<br>- Payment processing and transaction fees<br>- Order processing and administrative costs<br>- Production preparation and fulfillment system allocation<br>The remaining balance will be refunded to the original payment method.</p> <p><strong>2. Defective, Damaged, or Incorrect Items</strong></p> <p>If you receive an item that is <strong>defective, damaged during shipping, or incorrect</strong>, please contact us within <strong>72 hours after delivery confirmation.</strong><br>Your email must include:<br>- Your order number<br>- <strong>Clear photos</strong> of the product and the issue<br>- A brief description of the problem</p> <p>Please send your request to: contact@podcrewshop.com</p> <p>After review and approval, we will <strong>either</strong>:<br>- Send a <strong>free replacement</strong>, or<br>- Issue a <strong>full refund</strong></p> <p>We may request additional photos or information to verify the issue.<br>In some cases, we may request the defective item to be returned before processing the resolution.</p> <p><strong>3. Custom &amp; Made-To-Order Products</strong></p> <p>All products sold on WanderWild are <strong>custom-made or printed on demand.</strong><br>Because these products are made specifically for each order, <strong>we do not accept returns or refunds for the following reasons:</strong><br>- Incorrect size ordered<br>- Change of mind<br>- Incorrect shipping address provided by the customer<br>- Minor color differences due to screen display<br>- Custom name or personalization errors provided by the customer</p> <p>However, we understand mistakes happen. As a courtesy, we may offer <strong>a replacement with a 50% discount</strong> if you wish to reorder the correct size, color, or product.</p> <p><strong>4. Refund Processing</strong></p> <p>If your refund request is approved, refunds will be processed to your <strong>original payment method.</strong><br>Please allow <strong>5–7 business days</strong> for the refund to appear in your account depending on your bank or payment provider.<br>Once a refund has been issued, we will send a <strong>confirmation email.</strong></p> <p><strong>5. Late or Missing Refunds</strong></p> <p>If you have not received your refund:<br>- Check your bank account again.<br>- Contact your credit card company or payment provider.<br>- Contact your bank.</p> <p>Refunds can take several business days to process depending on your financial institution.<br>If 10 business days have passed since the refund confirmation and you still have not received the funds, please contact us at: contact@podcrewshop.com</p> <p><strong>6. Chargebacks &amp; Payment Disputes</strong></p> <p>If a chargeback or payment dispute is opened without contacting our support team first, we reserve the right to submit all order information, delivery confirmation, and communication records to the payment provider.<br>We are always happy to resolve any issues directly with our customers and encourage contacting us first for the fastest resolution.</p> | G3: =SUBSTITUTE(SUBSTITUTE(Templates!$B$3,"{{STORE}}",$A3),"{{EMAIL}}",$B3) -> <p><strong>Production Time</strong></p> <p>All products at WanderWild are made-to-order and produced specifically according to your selected design, size, and color. We do not keep inventory, which means each item is manufactured after your order is placed.<br>Production typically takes 5–10 business days (excluding weekends and holidays) before the order is shipped.<br>Orders enter the production process within 6 hours after being placed. Once production has started, orders cannot be modified or canceled.</p> <p><strong>Shipping Time</strong></p> <p>After production is completed, your order will be shipped according to the shipping method selected at checkout.</p> <p>Estimated delivery times:<br>Standard Shipping: 10–20 business days<br>Fast Shipping: 5–10 business days</p> <p>Delivery times may vary depending on your location, customs processing, and carrier delays.<br>Once your order has been shipped, you will receive a tracking number via email.</p> <p><strong>Estimated Delivery Time</strong></p> <p>Total estimated delivery time includes production time + shipping time.<br>Example:<br>- Standard Shipping: 15–30 business days total<br>- Fast Shipping: 10–20 business days total</p> <p>For the most accurate estimate, please check the estimated delivery date on your order confirmation email.<br>If you have any questions about your order, please contact us at: contact@podcrewshop.com</p> <p><strong>Shipping Cost</strong></p> <p>- $5.95 for orders under $90<br>- Free shipping for orders $90 and above</p> <p><strong>WanderWild is not responsible for delays caused by carriers, customs clearance, weather conditions, or peak holiday seasons.</strong></p> | H3: =SUBSTITUTE(SUBSTITUTE(SUBSTITUTE(SUBSTITUTE(SUBSTITUTE(Templates!$B$4,"{{STORE}}",$A3),"{{EMAIL}}",$B3),"{{DOMAIN}}",IF(C3<>"",C3,IFERROR(MID(B3,FIND("@",B3)+1,255),""))),"{{LAST_UPDATED}}",$E3),"{{ADDRESS_TEXT}}",IF(D3<>"",D3,"[Add mailing address]")) -> <p><strong>OVERVIEW</strong><br> Welcome to WanderWild! The terms “we”, “us” and “our” refer to WanderWild. WanderWild operates this store and website, including all related information, content, features, tools, products and services in order to provide you with a shopping experience. WanderWild is powered by Shopify. </p> <p>By visiting or using our Services, you agree to these Terms of Service.</p> <p><strong>SECTION 1 - ACCESS</strong><br> You must be at least the age of majority in your jurisdiction to use this website. </p> <p><strong>SECTION 2 - PRODUCTS</strong><br> Product colors may appear differently depending on your device display. </p> <p><strong>SECTION 3 - ORDERS</strong><br> We reserve the right to refuse or cancel orders at our discretion. </p> <p><strong>SECTION 4 - PRICES</strong><br> Prices may change without notice. </p> <p><strong>SECTION 5 - SHIPPING</strong><br> Delivery times are estimates only. </p> <p><strong>SECTION 6 - INTELLECTUAL PROPERTY</strong><br> All website content belongs to WanderWild or its licensors. </p> <p><strong>SECTION 7 - THIRD PARTY LINKS</strong><br> We are not responsible for third‑party websites linked from our store. </p> <p><strong>SECTION 8 - LIABILITY</strong><br> WanderWild is not liable for damages resulting from the use of this website. </p> <p><strong>SECTION 9 - CONTACT</strong><br> Questions about the Terms of Service should be sent to:<br> contact@podcrewshop.com </p> <hr> | I3: =SUBSTITUTE(SUBSTITUTE(SUBSTITUTE(SUBSTITUTE(SUBSTITUTE(Templates!$B$5,"{{STORE}}",$A3),"{{EMAIL}}",$B3),"{{DOMAIN}}",IF(C3<>"",C3,IFERROR(MID(B3,FIND("@",B3)+1,255),""))),"{{LAST_UPDATED}}",$E3),"{{ADDRESS_TEXT}}",IF(D3<>"",D3,"[Add mailing address]")) -> <p><strong>Last updated:</strong> March 12, 2026</p> <p> WanderWild operates this website and collects certain personal information to provide services. </p> <h2>Information We Collect</h2> <ul> <li>Name</li> <li>Email</li> <li>Shipping address</li> <li>Billing address</li> <li>Payment details</li> <li>Device information</li> </ul> <h2>How We Use Information</h2> <ul> <li>Process orders</li> <li>Provide support</li> <li>Improve the store</li> <li>Prevent fraud</li> </ul> <h2>Sharing Information</h2> <p> We may share information with Shopify, payment providers, and shipping partners to fulfill orders. </p> <h2>Cookies</h2> <p> Cookies are used to improve user experience and analyze website traffic. </p> <h2>Your Rights</h2> <p> You may request access, correction, or deletion of your personal information. </p> <h2>Security</h2> <p> We implement security measures to protect your data but cannot guarantee absolute security. </p> <h2>Contact</h2> <p> For privacy questions contact:<br> contact@podcrewshop.com </p>
A4: EliteTarget | B4: contact@podcrewshop.com | E4: March 12, 2026 | F4: =SUBSTITUTE(SUBSTITUTE(Templates!$B$2,"{{STORE}}",$A4),"{{EMAIL}}",$B4) -> <h4 style="text-align: center;">Refund, Replacement &amp; Cancellation Policy</h4> <p>At EliteTarget, each product is made to order and produced specifically for you after the order is placed. Because of this, we maintain a strict but fair refund and replacement policy.</p> <p><strong>1. Order Cancellation</strong></p> <p>Orders may be cancelled <strong>within 6 hours of placing the order.</strong><br>After this period, the order may already be in production and cannot be cancelled or modified.<br>To request a cancellation, please contact us immediately at: contact@podcrewshop.com</p> <p>Requests submitted after the 6-hour cancellation window cannot be guaranteed as the order may already be in production.</p> <p>If a cancellation request is approved within the allowed time window, a 30% management, processing, and transaction fee will be deducted from the total order value.<br>This fee covers costs that are non-recoverable once the order is placed, including but not limited to:<br>- Payment processing and transaction fees<br>- Order processing and administrative costs<br>- Production preparation and fulfillment system allocation<br>The remaining balance will be refunded to the original payment method.</p> <p><strong>2. Defective, Damaged, or Incorrect Items</strong></p> <p>If you receive an item that is <strong>defective, damaged during shipping, or incorrect</strong>, please contact us within <strong>72 hours after delivery confirmation.</strong><br>Your email must include:<br>- Your order number<br>- <strong>Clear photos</strong> of the product and the issue<br>- A brief description of the problem</p> <p>Please send your request to: contact@podcrewshop.com</p> <p>After review and approval, we will <strong>either</strong>:<br>- Send a <strong>free replacement</strong>, or<br>- Issue a <strong>full refund</strong></p> <p>We may request additional photos or information to verify the issue.<br>In some cases, we may request the defective item to be returned before processing the resolution.</p> <p><strong>3. Custom &amp; Made-To-Order Products</strong></p> <p>All products sold on EliteTarget are <strong>custom-made or printed on demand.</strong><br>Because these products are made specifically for each order, <strong>we do not accept returns or refunds for the following reasons:</strong><br>- Incorrect size ordered<br>- Change of mind<br>- Incorrect shipping address provided by the customer<br>- Minor color differences due to screen display<br>- Custom name or personalization errors provided by the customer</p> <p>However, we understand mistakes happen. As a courtesy, we may offer <strong>a replacement with a 50% discount</strong> if you wish to reorder the correct size, color, or product.</p> <p><strong>4. Refund Processing</strong></p> <p>If your refund request is approved, refunds will be processed to your <strong>original payment method.</strong><br>Please allow <strong>5–7 business days</strong> for the refund to appear in your account depending on your bank or payment provider.<br>Once a refund has been issued, we will send a <strong>confirmation email.</strong></p> <p><strong>5. Late or Missing Refunds</strong></p> <p>If you have not received your refund:<br>- Check your bank account again.<br>- Contact your credit card company or payment provider.<br>- Contact your bank.</p> <p>Refunds can take several business days to process depending on your financial institution.<br>If 10 business days have passed since the refund confirmation and you still have not received the funds, please contact us at: contact@podcrewshop.com</p> <p><strong>6. Chargebacks &amp; Payment Disputes</strong></p> <p>If a chargeback or payment dispute is opened without contacting our support team first, we reserve the right to submit all order information, delivery confirmation, and communication records to the payment provider.<br>We are always happy to resolve any issues directly with our customers and encourage contacting us first for the fastest resolution.</p> | G4: =SUBSTITUTE(SUBSTITUTE(Templates!$B$3,"{{STORE}}",$A4),"{{EMAIL}}",$B4) -> <p><strong>Production Time</strong></p> <p>All products at EliteTarget are made-to-order and produced specifically according to your selected design, size, and color. We do not keep inventory, which means each item is manufactured after your order is placed.<br>Production typically takes 5–10 business days (excluding weekends and holidays) before the order is shipped.<br>Orders enter the production process within 6 hours after being placed. Once production has started, orders cannot be modified or canceled.</p> <p><strong>Shipping Time</strong></p> <p>After production is completed, your order will be shipped according to the shipping method selected at checkout.</p> <p>Estimated delivery times:<br>Standard Shipping: 10–20 business days<br>Fast Shipping: 5–10 business days</p> <p>Delivery times may vary depending on your location, customs processing, and carrier delays.<br>Once your order has been shipped, you will receive a tracking number via email.</p> <p><strong>Estimated Delivery Time</strong></p> <p>Total estimated delivery time includes production time + shipping time.<br>Example:<br>- Standard Shipping: 15–30 business days total<br>- Fast Shipping: 10–20 business days total</p> <p>For the most accurate estimate, please check the estimated delivery date on your order confirmation email.<br>If you have any questions about your order, please contact us at: contact@podcrewshop.com</p> <p><strong>Shipping Cost</strong></p> <p>- $5.95 for orders under $90<br>- Free shipping for orders $90 and above</p> <p><strong>EliteTarget is not responsible for delays caused by carriers, customs clearance, weather conditions, or peak holiday seasons.</strong></p> | H4: =SUBSTITUTE(SUBSTITUTE(SUBSTITUTE(SUBSTITUTE(SUBSTITUTE(Templates!$B$4,"{{STORE}}",$A4),"{{EMAIL}}",$B4),"{{DOMAIN}}",IF(C4<>"",C4,IFERROR(MID(B4,FIND("@",B4)+1,255),""))),"{{LAST_UPDATED}}",$E4),"{{ADDRESS_TEXT}}",IF(D4<>"",D4,"[Add mailing address]")) -> <p><strong>OVERVIEW</strong><br> Welcome to EliteTarget! The terms “we”, “us” and “our” refer to EliteTarget. EliteTarget operates this store and website, including all related information, content, features, tools, products and services in order to provide you with a shopping experience. EliteTarget is powered by Shopify. </p> <p>By visiting or using our Services, you agree to these Terms of Service.</p> <p><strong>SECTION 1 - ACCESS</strong><br> You must be at least the age of majority in your jurisdiction to use this website. </p> <p><strong>SECTION 2 - PRODUCTS</strong><br> Product colors may appear differently depending on your device display. </p> <p><strong>SECTION 3 - ORDERS</strong><br> We reserve the right to refuse or cancel orders at our discretion. </p> <p><strong>SECTION 4 - PRICES</strong><br> Prices may change without notice. </p> <p><strong>SECTION 5 - SHIPPING</strong><br> Delivery times are estimates only. </p> <p><strong>SECTION 6 - INTELLECTUAL PROPERTY</strong><br> All website content belongs to EliteTarget or its licensors. </p> <p><strong>SECTION 7 - THIRD PARTY LINKS</strong><br> We are not responsible for third‑party websites linked from our store. </p> <p><strong>SECTION 8 - LIABILITY</strong><br> EliteTarget is not liable for damages resulting from the use of this website. </p> <p><strong>SECTION 9 - CONTACT</strong><br> Questions about the Terms of Service should be sent to:<br> contact@podcrewshop.com </p> <hr> | I4: =SUBSTITUTE(SUBSTITUTE(SUBSTITUTE(SUBSTITUTE(SUBSTITUTE(Templates!$B$5,"{{STORE}}",$A4),"{{EMAIL}}",$B4),"{{DOMAIN}}",IF(C4<>"",C4,IFERROR(MID(B4,FIND("@",B4)+1,255),""))),"{{LAST_UPDATED}}",$E4),"{{ADDRESS_TEXT}}",IF(D4<>"",D4,"[Add mailing address]")) -> <p><strong>Last updated:</strong> March 12, 2026</p> <p> EliteTarget operates this website and collects certain personal information to provide services. </p> <h2>Information We Collect</h2> <ul> <li>Name</li> <li>Email</li> <li>Shipping address</li> <li>Billing address</li> <li>Payment details</li> <li>Device information</li> </ul> <h2>How We Use Information</h2> <ul> <li>Process orders</li> <li>Provide support</li> <li>Improve the store</li> <li>Prevent fraud</li> </ul> <h2>Sharing Information</h2> <p> We may share information with Shopify, payment providers, and shipping partners to fulfill orders. </p> <h2>Cookies</h2> <p> Cookies are used to improve user experience and analyze website traffic. </p> <h2>Your Rights</h2> <p> You may request access, correction, or deletion of your personal information. </p> <h2>Security</h2> <p> We implement security measures to protect your data but cannot guarantee absolute security. </p> <h2>Contact</h2> <p> For privacy questions contact:<br> contact@podcrewshop.com </p>
A5: VictorySwing | B5: contact@podcrewshop.com | E5: March 12, 2026 | F5: =SUBSTITUTE(SUBSTITUTE(Templates!$B$2,"{{STORE}}",$A5),"{{EMAIL}}",$B5) -> <h4 style="text-align: center;">Refund, Replacement &amp; Cancellation Policy</h4> <p>At VictorySwing, each product is made to order and produced specifically for you after the order is placed. Because of this, we maintain a strict but fair refund and replacement policy.</p> <p><strong>1. Order Cancellation</strong></p> <p>Orders may be cancelled <strong>within 6 hours of placing the order.</strong><br>After this period, the order may already be in production and cannot be cancelled or modified.<br>To request a cancellation, please contact us immediately at: contact@podcrewshop.com</p> <p>Requests submitted after the 6-hour cancellation window cannot be guaranteed as the order may already be in production.</p> <p>If a cancellation request is approved within the allowed time window, a 30% management, processing, and transaction fee will be deducted from the total order value.<br>This fee covers costs that are non-recoverable once the order is placed, including but not limited to:<br>- Payment processing and transaction fees<br>- Order processing and administrative costs<br>- Production preparation and fulfillment system allocation<br>The remaining balance will be refunded to the original payment method.</p> <p><strong>2. Defective, Damaged, or Incorrect Items</strong></p> <p>If you receive an item that is <strong>defective, damaged during shipping, or incorrect</strong>, please contact us within <strong>72 hours after delivery confirmation.</strong><br>Your email must include:<br>- Your order number<br>- <strong>Clear photos</strong> of the product and the issue<br>- A brief description of the problem</p> <p>Please send your request to: contact@podcrewshop.com</p> <p>After review and approval, we will <strong>either</strong>:<br>- Send a <strong>free replacement</strong>, or<br>- Issue a <strong>full refund</strong></p> <p>We may request additional photos or information to verify the issue.<br>In some cases, we may request the defective item to be returned before processing the resolution.</p> <p><strong>3. Custom &amp; Made-To-Order Products</strong></p> <p>All products sold on VictorySwing are <strong>custom-made or printed on demand.</strong><br>Because these products are made specifically for each order, <strong>we do not accept returns or refunds for the following reasons:</strong><br>- Incorrect size ordered<br>- Change of mind<br>- Incorrect shipping address provided by the customer<br>- Minor color differences due to screen display<br>- Custom name or personalization errors provided by the customer</p> <p>However, we understand mistakes happen. As a courtesy, we may offer <strong>a replacement with a 50% discount</strong> if you wish to reorder the correct size, color, or product.</p> <p><strong>4. Refund Processing</strong></p> <p>If your refund request is approved, refunds will be processed to your <strong>original payment method.</strong><br>Please allow <strong>5–7 business days</strong> for the refund to appear in your account depending on your bank or payment provider.<br>Once a refund has been issued, we will send a <strong>confirmation email.</strong></p> <p><strong>5. Late or Missing Refunds</strong></p> <p>If you have not received your refund:<br>- Check your bank account again.<br>- Contact your credit card company or payment provider.<br>- Contact your bank.</p> <p>Refunds can take several business days to process depending on your financial institution.<br>If 10 business days have passed since the refund confirmation and you still have not received the funds, please contact us at: contact@podcrewshop.com</p> <p><strong>6. Chargebacks &amp; Payment Disputes</strong></p> <p>If a chargeback or payment dispute is opened without contacting our support team first, we reserve the right to submit all order information, delivery confirmation, and communication records to the payment provider.<br>We are always happy to resolve any issues directly with our customers and encourage contacting us first for the fastest resolution.</p> | G5: =SUBSTITUTE(SUBSTITUTE(Templates!$B$3,"{{STORE}}",$A5),"{{EMAIL}}",$B5) -> <p><strong>Production Time</strong></p> <p>All products at VictorySwing are made-to-order and produced specifically according to your selected design, size, and color. We do not keep inventory, which means each item is manufactured after your order is placed.<br>Production typically takes 5–10 business days (excluding weekends and holidays) before the order is shipped.<br>Orders enter the production process within 6 hours after being placed. Once production has started, orders cannot be modified or canceled.</p> <p><strong>Shipping Time</strong></p> <p>After production is completed, your order will be shipped according to the shipping method selected at checkout.</p> <p>Estimated delivery times:<br>Standard Shipping: 10–20 business days<br>Fast Shipping: 5–10 business days</p> <p>Delivery times may vary depending on your location, customs processing, and carrier delays.<br>Once your order has been shipped, you will receive a tracking number via email.</p> <p><strong>Estimated Delivery Time</strong></p> <p>Total estimated delivery time includes production time + shipping time.<br>Example:<br>- Standard Shipping: 15–30 business days total<br>- Fast Shipping: 10–20 business days total</p> <p>For the most accurate estimate, please check the estimated delivery date on your order confirmation email.<br>If you have any questions about your order, please contact us at: contact@podcrewshop.com</p> <p><strong>Shipping Cost</strong></p> <p>- $5.95 for orders under $90<br>- Free shipping for orders $90 and above</p> <p><strong>VictorySwing is not responsible for delays caused by carriers, customs clearance, weather conditions, or peak holiday seasons.</strong></p> | H5: =SUBSTITUTE(SUBSTITUTE(SUBSTITUTE(SUBSTITUTE(SUBSTITUTE(Templates!$B$4,"{{STORE}}",$A5),"{{EMAIL}}",$B5),"{{DOMAIN}}",IF(C5<>"",C5,IFERROR(MID(B5,FIND("@",B5)+1,255),""))),"{{LAST_UPDATED}}",$E5),"{{ADDRESS_TEXT}}",IF(D5<>"",D5,"[Add mailing address]")) -> <p><strong>OVERVIEW</strong><br> Welcome to VictorySwing! The terms “we”, “us” and “our” refer to VictorySwing. VictorySwing operates this store and website, including all related information, content, features, tools, products and services in order to provide you with a shopping experience. VictorySwing is powered by Shopify. </p> <p>By visiting or using our Services, you agree to these Terms of Service.</p> <p><strong>SECTION 1 - ACCESS</strong><br> You must be at least the age of majority in your jurisdiction to use this website. </p> <p><strong>SECTION 2 - PRODUCTS</strong><br> Product colors may appear differently depending on your device display. </p> <p><strong>SECTION 3 - ORDERS</strong><br> We reserve the right to refuse or cancel orders at our discretion. </p> <p><strong>SECTION 4 - PRICES</strong><br> Prices may change without notice. </p> <p><strong>SECTION 5 - SHIPPING</strong><br> Delivery times are estimates only. </p> <p><strong>SECTION 6 - INTELLECTUAL PROPERTY</strong><br> All website content belongs to VictorySwing or its licensors. </p> <p><strong>SECTION 7 - THIRD PARTY LINKS</strong><br> We are not responsible for third‑party websites linked from our store. </p> <p><strong>SECTION 8 - LIABILITY</strong><br> VictorySwing is not liable for damages resulting from the use of this website. </p> <p><strong>SECTION 9 - CONTACT</strong><br> Questions about the Terms of Service should be sent to:<br> contact@podcrewshop.com </p> <hr> | I5: =SUBSTITUTE(SUBSTITUTE(SUBSTITUTE(SUBSTITUTE(SUBSTITUTE(Templates!$B$5,"{{STORE}}",$A5),"{{EMAIL}}",$B5),"{{DOMAIN}}",IF(C5<>"",C5,IFERROR(MID(B5,FIND("@",B5)+1,255),""))),"{{LAST_UPDATED}}",$E5),"{{ADDRESS_TEXT}}",IF(D5<>"",D5,"[Add mailing address]")) -> <p><strong>Last updated:</strong> March 12, 2026</p> <p> VictorySwing operates this website and collects certain personal information to provide services. </p> <h2>Information We Collect</h2> <ul> <li>Name</li> <li>Email</li> <li>Shipping address</li> <li>Billing address</li> <li>Payment details</li> <li>Device information</li> </ul> <h2>How We Use Information</h2> <ul> <li>Process orders</li> <li>Provide support</li> <li>Improve the store</li> <li>Prevent fraud</li> </ul> <h2>Sharing Information</h2> <p> We may share information with Shopify, payment providers, and shipping partners to fulfill orders. </p> <h2>Cookies</h2> <p> Cookies are used to improve user experience and analyze website traffic. </p> <h2>Your Rights</h2> <p> You may request access, correction, or deletion of your personal information. </p> <h2>Security</h2> <p> We implement security measures to protect your data but cannot guarantee absolute security. </p> <h2>Contact</h2> <p> For privacy questions contact:<br> contact@podcrewshop.com </p>
A6: PrecisionPlay | B6: contact@podcrewshop.com | E6: March 12, 2026 | F6: =SUBSTITUTE(SUBSTITUTE(Templates!$B$2,"{{STORE}}",$A6),"{{EMAIL}}",$B6) -> <h4 style="text-align: center;">Refund, Replacement &amp; Cancellation Policy</h4> <p>At PrecisionPlay, each product is made to order and produced specifically for you after the order is placed. Because of this, we maintain a strict but fair refund and replacement policy.</p> <p><strong>1. Order Cancellation</strong></p> <p>Orders may be cancelled <strong>within 6 hours of placing the order.</strong><br>After this period, the order may already be in production and cannot be cancelled or modified.<br>To request a cancellation, please contact us immediately at: contact@podcrewshop.com</p> <p>Requests submitted after the 6-hour cancellation window cannot be guaranteed as the order may already be in production.</p> <p>If a cancellation request is approved within the allowed time window, a 30% management, processing, and transaction fee will be deducted from the total order value.<br>This fee covers costs that are non-recoverable once the order is placed, including but not limited to:<br>- Payment processing and transaction fees<br>- Order processing and administrative costs<br>- Production preparation and fulfillment system allocation<br>The remaining balance will be refunded to the original payment method.</p> <p><strong>2. Defective, Damaged, or Incorrect Items</strong></p> <p>If you receive an item that is <strong>defective, damaged during shipping, or incorrect</strong>, please contact us within <strong>72 hours after delivery confirmation.</strong><br>Your email must include:<br>- Your order number<br>- <strong>Clear photos</strong> of the product and the issue<br>- A brief description of the problem</p> <p>Please send your request to: contact@podcrewshop.com</p> <p>After review and approval, we will <strong>either</strong>:<br>- Send a <strong>free replacement</strong>, or<br>- Issue a <strong>full refund</strong></p> <p>We may request additional photos or information to verify the issue.<br>In some cases, we may request the defective item to be returned before processing the resolution.</p> <p><strong>3. Custom &amp; Made-To-Order Products</strong></p> <p>All products sold on PrecisionPlay are <strong>custom-made or printed on demand.</strong><br>Because these products are made specifically for each order, <strong>we do not accept returns or refunds for the following reasons:</strong><br>- Incorrect size ordered<br>- Change of mind<br>- Incorrect shipping address provided by the customer<br>- Minor color differences due to screen display<br>- Custom name or personalization errors provided by the customer</p> <p>However, we understand mistakes happen. As a courtesy, we may offer <strong>a replacement with a 50% discount</strong> if you wish to reorder the correct size, color, or product.</p> <p><strong>4. Refund Processing</strong></p> <p>If your refund request is approved, refunds will be processed to your <strong>original payment method.</strong><br>Please allow <strong>5–7 business days</strong> for the refund to appear in your account depending on your bank or payment provider.<br>Once a refund has been issued, we will send a <strong>confirmation email.</strong></p> <p><strong>5. Late or Missing Refunds</strong></p> <p>If you have not received your refund:<br>- Check your bank account again.<br>- Contact your credit card company or payment provider.<br>- Contact your bank.</p> <p>Refunds can take several business days to process depending on your financial institution.<br>If 10 business days have passed since the refund confirmation and you still have not received the funds, please contact us at: contact@podcrewshop.com</p> <p><strong>6. Chargebacks &amp; Payment Disputes</strong></p> <p>If a chargeback or payment dispute is opened without contacting our support team first, we reserve the right to submit all order information, delivery confirmation, and communication records to the payment provider.<br>We are always happy to resolve any issues directly with our customers and encourage contacting us first for the fastest resolution.</p> | G6: =SUBSTITUTE(SUBSTITUTE(Templates!$B$3,"{{STORE}}",$A6),"{{EMAIL}}",$B6) -> <p><strong>Production Time</strong></p> <p>All products at PrecisionPlay are made-to-order and produced specifically according to your selected design, size, and color. We do not keep inventory, which means each item is manufactured after your order is placed.<br>Production typically takes 5–10 business days (excluding weekends and holidays) before the order is shipped.<br>Orders enter the production process within 6 hours after being placed. Once production has started, orders cannot be modified or canceled.</p> <p><strong>Shipping Time</strong></p> <p>After production is completed, your order will be shipped according to the shipping method selected at checkout.</p> <p>Estimated delivery times:<br>Standard Shipping: 10–20 business days<br>Fast Shipping: 5–10 business days</p> <p>Delivery times may vary depending on your location, customs processing, and carrier delays.<br>Once your order has been shipped, you will receive a tracking number via email.</p> <p><strong>Estimated Delivery Time</strong></p> <p>Total estimated delivery time includes production time + shipping time.<br>Example:<br>- Standard Shipping: 15–30 business days total<br>- Fast Shipping: 10–20 business days total</p> <p>For the most accurate estimate, please check the estimated delivery date on your order confirmation email.<br>If you have any questions about your order, please contact us at: contact@podcrewshop.com</p> <p><strong>Shipping Cost</strong></p> <p>- $5.95 for orders under $90<br>- Free shipping for orders $90 and above</p> <p><strong>PrecisionPlay is not responsible for delays caused by carriers, customs clearance, weather conditions, or peak holiday seasons.</strong></p> | H6: =SUBSTITUTE(SUBSTITUTE(SUBSTITUTE(SUBSTITUTE(SUBSTITUTE(Templates!$B$4,"{{STORE}}",$A6),"{{EMAIL}}",$B6),"{{DOMAIN}}",IF(C6<>"",C6,IFERROR(MID(B6,FIND("@",B6)+1,255),""))),"{{LAST_UPDATED}}",$E6),"{{ADDRESS_TEXT}}",IF(D6<>"",D6,"[Add mailing address]")) -> <p><strong>OVERVIEW</strong><br> Welcome to PrecisionPlay! The terms “we”, “us” and “our” refer to PrecisionPlay. PrecisionPlay operates this store and website, including all related information, content, features, tools, products and services in order to provide you with a shopping experience. PrecisionPlay is powered by Shopify. </p> <p>By visiting or using our Services, you agree to these Terms of Service.</p> <p><strong>SECTION 1 - ACCESS</strong><br> You must be at least the age of majority in your jurisdiction to use this website. </p> <p><strong>SECTION 2 - PRODUCTS</strong><br> Product colors may appear differently depending on your device display. </p> <p><strong>SECTION 3 - ORDERS</strong><br> We reserve the right to refuse or cancel orders at our discretion. </p> <p><strong>SECTION 4 - PRICES</strong><br> Prices may change without notice. </p> <p><strong>SECTION 5 - SHIPPING</strong><br> Delivery times are estimates only. </p> <p><strong>SECTION 6 - INTELLECTUAL PROPERTY</strong><br> All website content belongs to PrecisionPlay or its licensors. </p> <p><strong>SECTION 7 - THIRD PARTY LINKS</strong><br> We are not responsible for third‑party websites linked from our store. </p> <p><strong>SECTION 8 - LIABILITY</strong><br> PrecisionPlay is not liable for damages resulting from the use of this website. </p> <p><strong>SECTION 9 - CONTACT</strong><br> Questions about the Terms of Service should be sent to:<br> contact@podcrewshop.com </p> <hr> | I6: =SUBSTITUTE(SUBSTITUTE(SUBSTITUTE(SUBSTITUTE(SUBSTITUTE(Templates!$B$5,"{{STORE}}",$A6),"{{EMAIL}}",$B6),"{{DOMAIN}}",IF(C6<>"",C6,IFERROR(MID(B6,FIND("@",B6)+1,255),""))),"{{LAST_UPDATED}}",$E6),"{{ADDRESS_TEXT}}",IF(D6<>"",D6,"[Add mailing address]")) -> <p><strong>Last updated:</strong> March 12, 2026</p> <p> PrecisionPlay operates this website and collects certain personal information to provide services. </p> <h2>Information We Collect</h2> <ul> <li>Name</li> <li>Email</li> <li>Shipping address</li> <li>Billing address</li> <li>Payment details</li> <li>Device information</li> </ul> <h2>How We Use Information</h2> <ul> <li>Process orders</li> <li>Provide support</li> <li>Improve the store</li> <li>Prevent fraud</li> </ul> <h2>Sharing Information</h2> <p> We may share information with Shopify, payment providers, and shipping partners to fulfill orders. </p> <h2>Cookies</h2> <p> Cookies are used to improve user experience and analyze website traffic. </p> <h2>Your Rights</h2> <p> You may request access, correction, or deletion of your personal information. </p> <h2>Security</h2> <p> We implement security measures to protect your data but cannot guarantee absolute security. </p> <h2>Contact</h2> <p> For privacy questions contact:<br> contact@podcrewshop.com </p> | J6: vvv
A7: TrailForge | B7: contact@podcrewshop.com | E7: March 12, 2026 | F7: =SUBSTITUTE(SUBSTITUTE(Templates!$B$2,"{{STORE}}",$A7),"{{EMAIL}}",$B7) -> <h4 style="text-align: center;">Refund, Replacement &amp; Cancellation Policy</h4> <p>At TrailForge, each product is made to order and produced specifically for you after the order is placed. Because of this, we maintain a strict but fair refund and replacement policy.</p> <p><strong>1. Order Cancellation</strong></p> <p>Orders may be cancelled <strong>within 6 hours of placing the order.</strong><br>After this period, the order may already be in production and cannot be cancelled or modified.<br>To request a cancellation, please contact us immediately at: contact@podcrewshop.com</p> <p>Requests submitted after the 6-hour cancellation window cannot be guaranteed as the order may already be in production.</p> <p>If a cancellation request is approved within the allowed time window, a 30% management, processing, and transaction fee will be deducted from the total order value.<br>This fee covers costs that are non-recoverable once the order is placed, including but not limited to:<br>- Payment processing and transaction fees<br>- Order processing and administrative costs<br>- Production preparation and fulfillment system allocation<br>The remaining balance will be refunded to the original payment method.</p> <p><strong>2. Defective, Damaged, or Incorrect Items</strong></p> <p>If you receive an item that is <strong>defective, damaged during shipping, or incorrect</strong>, please contact us within <strong>72 hours after delivery confirmation.</strong><br>Your email must include:<br>- Your order number<br>- <strong>Clear photos</strong> of the product and the issue<br>- A brief description of the problem</p> <p>Please send your request to: contact@podcrewshop.com</p> <p>After review and approval, we will <strong>either</strong>:<br>- Send a <strong>free replacement</strong>, or<br>- Issue a <strong>full refund</strong></p> <p>We may request additional photos or information to verify the issue.<br>In some cases, we may request the defective item to be returned before processing the resolution.</p> <p><strong>3. Custom &amp; Made-To-Order Products</strong></p> <p>All products sold on TrailForge are <strong>custom-made or printed on demand.</strong><br>Because these products are made specifically for each order, <strong>we do not accept returns or refunds for the following reasons:</strong><br>- Incorrect size ordered<br>- Change of mind<br>- Incorrect shipping address provided by the customer<br>- Minor color differences due to screen display<br>- Custom name or personalization errors provided by the customer</p> <p>However, we understand mistakes happen. As a courtesy, we may offer <strong>a replacement with a 50% discount</strong> if you wish to reorder the correct size, color, or product.</p> <p><strong>4. Refund Processing</strong></p> <p>If your refund request is approved, refunds will be processed to your <strong>original payment method.</strong><br>Please allow <strong>5–7 business days</strong> for the refund to appear in your account depending on your bank or payment provider.<br>Once a refund has been issued, we will send a <strong>confirmation email.</strong></p> <p><strong>5. Late or Missing Refunds</strong></p> <p>If you have not received your refund:<br>- Check your bank account again.<br>- Contact your credit card company or payment provider.<br>- Contact your bank.</p> <p>Refunds can take several business days to process depending on your financial institution.<br>If 10 business days have passed since the refund confirmation and you still have not received the funds, please contact us at: contact@podcrewshop.com</p> <p><strong>6. Chargebacks &amp; Payment Disputes</strong></p> <p>If a chargeback or payment dispute is opened without contacting our support team first, we reserve the right to submit all order information, delivery confirmation, and communication records to the payment provider.<br>We are always happy to resolve any issues directly with our customers and encourage contacting us first for the fastest resolution.</p> | G7: =SUBSTITUTE(SUBSTITUTE(Templates!$B$3,"{{STORE}}",$A7),"{{EMAIL}}",$B7) -> <p><strong>Production Time</strong></p> <p>All products at TrailForge are made-to-order and produced specifically according to your selected design, size, and color. We do not keep inventory, which means each item is manufactured after your order is placed.<br>Production typically takes 5–10 business days (excluding weekends and holidays) before the order is shipped.<br>Orders enter the production process within 6 hours after being placed. Once production has started, orders cannot be modified or canceled.</p> <p><strong>Shipping Time</strong></p> <p>After production is completed, your order will be shipped according to the shipping method selected at checkout.</p> <p>Estimated delivery times:<br>Standard Shipping: 10–20 business days<br>Fast Shipping: 5–10 business days</p> <p>Delivery times may vary depending on your location, customs processing, and carrier delays.<br>Once your order has been shipped, you will receive a tracking number via email.</p> <p><strong>Estimated Delivery Time</strong></p> <p>Total estimated delivery time includes production time + shipping time.<br>Example:<br>- Standard Shipping: 15–30 business days total<br>- Fast Shipping: 10–20 business days total</p> <p>For the most accurate estimate, please check the estimated delivery date on your order confirmation email.<br>If you have any questions about your order, please contact us at: contact@podcrewshop.com</p> <p><strong>Shipping Cost</strong></p> <p>- $5.95 for orders under $90<br>- Free shipping for orders $90 and above</p> <p><strong>TrailForge is not responsible for delays caused by carriers, customs clearance, weather conditions, or peak holiday seasons.</strong></p> | H7: =SUBSTITUTE(SUBSTITUTE(SUBSTITUTE(SUBSTITUTE(SUBSTITUTE(Templates!$B$4,"{{STORE}}",$A7),"{{EMAIL}}",$B7),"{{DOMAIN}}",IF(C7<>"",C7,IFERROR(MID(B7,FIND("@",B7)+1,255),""))),"{{LAST_UPDATED}}",$E7),"{{ADDRESS_TEXT}}",IF(D7<>"",D7,"[Add mailing address]")) -> <p><strong>OVERVIEW</strong><br> Welcome to TrailForge! The terms “we”, “us” and “our” refer to TrailForge. TrailForge operates this store and website, including all related information, content, features, tools, products and services in order to provide you with a shopping experience. TrailForge is powered by Shopify. </p> <p>By visiting or using our Services, you agree to these Terms of Service.</p> <p><strong>SECTION 1 - ACCESS</strong><br> You must be at least the age of majority in your jurisdiction to use this website. </p> <p><strong>SECTION 2 - PRODUCTS</strong><br> Product colors may appear differently depending on your device display. </p> <p><strong>SECTION 3 - ORDERS</strong><br> We reserve the right to refuse or cancel orders at our discretion. </p> <p><strong>SECTION 4 - PRICES</strong><br> Prices may change without notice. </p> <p><strong>SECTION 5 - SHIPPING</strong><br> Delivery times are estimates only. </p> <p><strong>SECTION 6 - INTELLECTUAL PROPERTY</strong><br> All website content belongs to TrailForge or its licensors. </p> <p><strong>SECTION 7 - THIRD PARTY LINKS</strong><br> We are not responsible for third‑party websites linked from our store. </p> <p><strong>SECTION 8 - LIABILITY</strong><br> TrailForge is not liable for damages resulting from the use of this website. </p> <p><strong>SECTION 9 - CONTACT</strong><br> Questions about the Terms of Service should be sent to:<br> contact@podcrewshop.com </p> <hr> | I7: =SUBSTITUTE(SUBSTITUTE(SUBSTITUTE(SUBSTITUTE(SUBSTITUTE(Templates!$B$5,"{{STORE}}",$A7),"{{EMAIL}}",$B7),"{{DOMAIN}}",IF(C7<>"",C7,IFERROR(MID(B7,FIND("@",B7)+1,255),""))),"{{LAST_UPDATED}}",$E7),"{{ADDRESS_TEXT}}",IF(D7<>"",D7,"[Add mailing address]")) -> <p><strong>Last updated:</strong> March 12, 2026</p> <p> TrailForge operates this website and collects certain personal information to provide services. </p> <h2>Information We Collect</h2> <ul> <li>Name</li> <li>Email</li> <li>Shipping address</li> <li>Billing address</li> <li>Payment details</li> <li>Device information</li> </ul> <h2>How We Use Information</h2> <ul> <li>Process orders</li> <li>Provide support</li> <li>Improve the store</li> <li>Prevent fraud</li> </ul> <h2>Sharing Information</h2> <p> We may share information with Shopify, payment providers, and shipping partners to fulfill orders. </p> <h2>Cookies</h2> <p> Cookies are used to improve user experience and analyze website traffic. </p> <h2>Your Rights</h2> <p> You may request access, correction, or deletion of your personal information. </p> <h2>Security</h2> <p> We implement security measures to protect your data but cannot guarantee absolute security. </p> <h2>Contact</h2> <p> For privacy questions contact:<br> contact@podcrewshop.com </p>
A8: MountainEcho | B8: contact@podcrewshop.com | E8: March 12, 2026 | F8: =SUBSTITUTE(SUBSTITUTE(Templates!$B$2,"{{STORE}}",$A8),"{{EMAIL}}",$B8) -> <h4 style="text-align: center;">Refund, Replacement &amp; Cancellation Policy</h4> <p>At MountainEcho, each product is made to order and produced specifically for you after the order is placed. Because of this, we maintain a strict but fair refund and replacement policy.</p> <p><strong>1. Order Cancellation</strong></p> <p>Orders may be cancelled <strong>within 6 hours of placing the order.</strong><br>After this period, the order may already be in production and cannot be cancelled or modified.<br>To request a cancellation, please contact us immediately at: contact@podcrewshop.com</p> <p>Requests submitted after the 6-hour cancellation window cannot be guaranteed as the order may already be in production.</p> <p>If a cancellation request is approved within the allowed time window, a 30% management, processing, and transaction fee will be deducted from the total order value.<br>This fee covers costs that are non-recoverable once the order is placed, including but not limited to:<br>- Payment processing and transaction fees<br>- Order processing and administrative costs<br>- Production preparation and fulfillment system allocation<br>The remaining balance will be refunded to the original payment method.</p> <p><strong>2. Defective, Damaged, or Incorrect Items</strong></p> <p>If you receive an item that is <strong>defective, damaged during shipping, or incorrect</strong>, please contact us within <strong>72 hours after delivery confirmation.</strong><br>Your email must include:<br>- Your order number<br>- <strong>Clear photos</strong> of the product and the issue<br>- A brief description of the problem</p> <p>Please send your request to: contact@podcrewshop.com</p> <p>After review and approval, we will <strong>either</strong>:<br>- Send a <strong>free replacement</strong>, or<br>- Issue a <strong>full refund</strong></p> <p>We may request additional photos or information to verify the issue.<br>In some cases, we may request the defective item to be returned before processing the resolution.</p> <p><strong>3. Custom &amp; Made-To-Order Products</strong></p> <p>All products sold on MountainEcho are <strong>custom-made or printed on demand.</strong><br>Because these products are made specifically for each order, <strong>we do not accept returns or refunds for the following reasons:</strong><br>- Incorrect size ordered<br>- Change of mind<br>- Incorrect shipping address provided by the customer<br>- Minor color differences due to screen display<br>- Custom name or personalization errors provided by the customer</p> <p>However, we understand mistakes happen. As a courtesy, we may offer <strong>a replacement with a 50% discount</strong> if you wish to reorder the correct size, color, or product.</p> <p><strong>4. Refund Processing</strong></p> <p>If your refund request is approved, refunds will be processed to your <strong>original payment method.</strong><br>Please allow <strong>5–7 business days</strong> for the refund to appear in your account depending on your bank or payment provider.<br>Once a refund has been issued, we will send a <strong>confirmation email.</strong></p> <p><strong>5. Late or Missing Refunds</strong></p> <p>If you have not received your refund:<br>- Check your bank account again.<br>- Contact your credit card company or payment provider.<br>- Contact your bank.</p> <p>Refunds can take several business days to process depending on your financial institution.<br>If 10 business days have passed since the refund confirmation and you still have not received the funds, please contact us at: contact@podcrewshop.com</p> <p><strong>6. Chargebacks &amp; Payment Disputes</strong></p> <p>If a chargeback or payment dispute is opened without contacting our support team first, we reserve the right to submit all order information, delivery confirmation, and communication records to the payment provider.<br>We are always happy to resolve any issues directly with our customers and encourage contacting us first for the fastest resolution.</p> | G8: =SUBSTITUTE(SUBSTITUTE(Templates!$B$3,"{{STORE}}",$A8),"{{EMAIL}}",$B8) -> <p><strong>Production Time</strong></p> <p>All products at MountainEcho are made-to-order and produced specifically according to your selected design, size, and color. We do not keep inventory, which means each item is manufactured after your order is placed.<br>Production typically takes 5–10 business days (excluding weekends and holidays) before the order is shipped.<br>Orders enter the production process within 6 hours after being placed. Once production has started, orders cannot be modified or canceled.</p> <p><strong>Shipping Time</strong></p> <p>After production is completed, your order will be shipped according to the shipping method selected at checkout.</p> <p>Estimated delivery times:<br>Standard Shipping: 10–20 business days<br>Fast Shipping: 5–10 business days</p> <p>Delivery times may vary depending on your location, customs processing, and carrier delays.<br>Once your order has been shipped, you will receive a tracking number via email.</p> <p><strong>Estimated Delivery Time</strong></p> <p>Total estimated delivery time includes production time + shipping time.<br>Example:<br>- Standard Shipping: 15–30 business days total<br>- Fast Shipping: 10–20 business days total</p> <p>For the most accurate estimate, please check the estimated delivery date on your order confirmation email.<br>If you have any questions about your order, please contact us at: contact@podcrewshop.com</p> <p><strong>Shipping Cost</strong></p> <p>- $5.95 for orders under $90<br>- Free shipping for orders $90 and above</p> <p><strong>MountainEcho is not responsible for delays caused by carriers, customs clearance, weather conditions, or peak holiday seasons.</strong></p> | H8: =SUBSTITUTE(SUBSTITUTE(SUBSTITUTE(SUBSTITUTE(SUBSTITUTE(Templates!$B$4,"{{STORE}}",$A8),"{{EMAIL}}",$B8),"{{DOMAIN}}",IF(C8<>"",C8,IFERROR(MID(B8,FIND("@",B8)+1,255),""))),"{{LAST_UPDATED}}",$E8),"{{ADDRESS_TEXT}}",IF(D8<>"",D8,"[Add mailing address]")) -> <p><strong>OVERVIEW</strong><br> Welcome to MountainEcho! The terms “we”, “us” and “our” refer to MountainEcho. MountainEcho operates this store and website, including all related information, content, features, tools, products and services in order to provide you with a shopping experience. MountainEcho is powered by Shopify. </p> <p>By visiting or using our Services, you agree to these Terms of Service.</p> <p><strong>SECTION 1 - ACCESS</strong><br> You must be at least the age of majority in your jurisdiction to use this website. </p> <p><strong>SECTION 2 - PRODUCTS</strong><br> Product colors may appear differently depending on your device display. </p> <p><strong>SECTION 3 - ORDERS</strong><br> We reserve the right to refuse or cancel orders at our discretion. </p> <p><strong>SECTION 4 - PRICES</strong><br> Prices may change without notice. </p> <p><strong>SECTION 5 - SHIPPING</strong><br> Delivery times are estimates only. </p> <p><strong>SECTION 6 - INTELLECTUAL PROPERTY</strong><br> All website content belongs to MountainEcho or its licensors. </p> <p><strong>SECTION 7 - THIRD PARTY LINKS</strong><br> We are not responsible for third‑party websites linked from our store. </p> <p><strong>SECTION 8 - LIABILITY</strong><br> MountainEcho is not liable for damages resulting from the use of this website. </p> <p><strong>SECTION 9 - CONTACT</strong><br> Questions about the Terms of Service should be sent to:<br> contact@podcrewshop.com </p> <hr> | I8: =SUBSTITUTE(SUBSTITUTE(SUBSTITUTE(SUBSTITUTE(SUBSTITUTE(Templates!$B$5,"{{STORE}}",$A8),"{{EMAIL}}",$B8),"{{DOMAIN}}",IF(C8<>"",C8,IFERROR(MID(B8,FIND("@",B8)+1,255),""))),"{{LAST_UPDATED}}",$E8),"{{ADDRESS_TEXT}}",IF(D8<>"",D8,"[Add mailing address]")) -> <p><strong>Last updated:</strong> March 12, 2026</p> <p> MountainEcho operates this website and collects certain personal information to provide services. </p> <h2>Information We Collect</h2> <ul> <li>Name</li> <li>Email</li> <li>Shipping address</li> <li>Billing address</li> <li>Payment details</li> <li>Device information</li> </ul> <h2>How We Use Information</h2> <ul> <li>Process orders</li> <li>Provide support</li> <li>Improve the store</li> <li>Prevent fraud</li> </ul> <h2>Sharing Information</h2> <p> We may share information with Shopify, payment providers, and shipping partners to fulfill orders. </p> <h2>Cookies</h2> <p> Cookies are used to improve user experience and analyze website traffic. </p> <h2>Your Rights</h2> <p> You may request access, correction, or deletion of your personal information. </p> <h2>Security</h2> <p> We implement security measures to protect your data but cannot guarantee absolute security. </p> <h2>Contact</h2> <p> For privacy questions contact:<br> contact@podcrewshop.com </p>
A9: SummitCamp | B9: contact@podcrewshop.com | E9: March 12, 2026 | F9: =SUBSTITUTE(SUBSTITUTE(Templates!$B$2,"{{STORE}}",$A9),"{{EMAIL}}",$B9) -> <h4 style="text-align: center;">Refund, Replacement &amp; Cancellation Policy</h4> <p>At SummitCamp, each product is made to order and produced specifically for you after the order is placed. Because of this, we maintain a strict but fair refund and replacement policy.</p> <p><strong>1. Order Cancellation</strong></p> <p>Orders may be cancelled <strong>within 6 hours of placing the order.</strong><br>After this period, the order may already be in production and cannot be cancelled or modified.<br>To request a cancellation, please contact us immediately at: contact@podcrewshop.com</p> <p>Requests submitted after the 6-hour cancellation window cannot be guaranteed as the order may already be in production.</p> <p>If a cancellation request is approved within the allowed time window, a 30% management, processing, and transaction fee will be deducted from the total order value.<br>This fee covers costs that are non-recoverable once the order is placed, including but not limited to:<br>- Payment processing and transaction fees<br>- Order processing and administrative costs<br>- Production preparation and fulfillment system allocation<br>The remaining balance will be refunded to the original payment method.</p> <p><strong>2. Defective, Damaged, or Incorrect Items</strong></p> <p>If you receive an item that is <strong>defective, damaged during shipping, or incorrect</strong>, please contact us within <strong>72 hours after delivery confirmation.</strong><br>Your email must include:<br>- Your order number<br>- <strong>Clear photos</strong> of the product and the issue<br>- A brief description of the problem</p> <p>Please send your request to: contact@podcrewshop.com</p> <p>After review and approval, we will <strong>either</strong>:<br>- Send a <strong>free replacement</strong>, or<br>- Issue a <strong>full refund</strong></p> <p>We may request additional photos or information to verify the issue.<br>In some cases, we may request the defective item to be returned before processing the resolution.</p> <p><strong>3. Custom &amp; Made-To-Order Products</strong></p> <p>All products sold on SummitCamp are <strong>custom-made or printed on demand.</strong><br>Because these products are made specifically for each order, <strong>we do not accept returns or refunds for the following reasons:</strong><br>- Incorrect size ordered<br>- Change of mind<br>- Incorrect shipping address provided by the customer<br>- Minor color differences due to screen display<br>- Custom name or personalization errors provided by the customer</p> <p>However, we understand mistakes happen. As a courtesy, we may offer <strong>a replacement with a 50% discount</strong> if you wish to reorder the correct size, color, or product.</p> <p><strong>4. Refund Processing</strong></p> <p>If your refund request is approved, refunds will be processed to your <strong>original payment method.</strong><br>Please allow <strong>5–7 business days</strong> for the refund to appear in your account depending on your bank or payment provider.<br>Once a refund has been issued, we will send a <strong>confirmation email.</strong></p> <p><strong>5. Late or Missing Refunds</strong></p> <p>If you have not received your refund:<br>- Check your bank account again.<br>- Contact your credit card company or payment provider.<br>- Contact your bank.</p> <p>Refunds can take several business days to process depending on your financial institution.<br>If 10 business days have passed since the refund confirmation and you still have not received the funds, please contact us at: contact@podcrewshop.com</p> <p><strong>6. Chargebacks &amp; Payment Disputes</strong></p> <p>If a chargeback or payment dispute is opened without contacting our support team first, we reserve the right to submit all order information, delivery confirmation, and communication records to the payment provider.<br>We are always happy to resolve any issues directly with our customers and encourage contacting us first for the fastest resolution.</p> | G9: =SUBSTITUTE(SUBSTITUTE(Templates!$B$3,"{{STORE}}",$A9),"{{EMAIL}}",$B9) -> <p><strong>Production Time</strong></p> <p>All products at SummitCamp are made-to-order and produced specifically according to your selected design, size, and color. We do not keep inventory, which means each item is manufactured after your order is placed.<br>Production typically takes 5–10 business days (excluding weekends and holidays) before the order is shipped.<br>Orders enter the production process within 6 hours after being placed. Once production has started, orders cannot be modified or canceled.</p> <p><strong>Shipping Time</strong></p> <p>After production is completed, your order will be shipped according to the shipping method selected at checkout.</p> <p>Estimated delivery times:<br>Standard Shipping: 10–20 business days<br>Fast Shipping: 5–10 business days</p> <p>Delivery times may vary depending on your location, customs processing, and carrier delays.<br>Once your order has been shipped, you will receive a tracking number via email.</p> <p><strong>Estimated Delivery Time</strong></p> <p>Total estimated delivery time includes production time + shipping time.<br>Example:<br>- Standard Shipping: 15–30 business days total<br>- Fast Shipping: 10–20 business days total</p> <p>For the most accurate estimate, please check the estimated delivery date on your order confirmation email.<br>If you have any questions about your order, please contact us at: contact@podcrewshop.com</p> <p><strong>Shipping Cost</strong></p> <p>- $5.95 for orders under $90<br>- Free shipping for orders $90 and above</p> <p><strong>SummitCamp is not responsible for delays caused by carriers, customs clearance, weather conditions, or peak holiday seasons.</strong></p> | H9: =SUBSTITUTE(SUBSTITUTE(SUBSTITUTE(SUBSTITUTE(SUBSTITUTE(Templates!$B$4,"{{STORE}}",$A9),"{{EMAIL}}",$B9),"{{DOMAIN}}",IF(C9<>"",C9,IFERROR(MID(B9,FIND("@",B9)+1,255),""))),"{{LAST_UPDATED}}",$E9),"{{ADDRESS_TEXT}}",IF(D9<>"",D9,"[Add mailing address]")) -> <p><strong>OVERVIEW</strong><br> Welcome to SummitCamp! The terms “we”, “us” and “our” refer to SummitCamp. SummitCamp operates this store and website, including all related information, content, features, tools, products and services in order to provide you with a shopping experience. SummitCamp is powered by Shopify. </p> <p>By visiting or using our Services, you agree to these Terms of Service.</p> <p><strong>SECTION 1 - ACCESS</strong><br> You must be at least the age of majority in your jurisdiction to use this website. </p> <p><strong>SECTION 2 - PRODUCTS</strong><br> Product colors may appear differently depending on your device display. </p> <p><strong>SECTION 3 - ORDERS</strong><br> We reserve the right to refuse or cancel orders at our discretion. </p> <p><strong>SECTION 4 - PRICES</strong><br> Prices may change without notice. </p> <p><strong>SECTION 5 - SHIPPING</strong><br> Delivery times are estimates only. </p> <p><strong>SECTION 6 - INTELLECTUAL PROPERTY</strong><br> All website content belongs to SummitCamp or its licensors. </p> <p><strong>SECTION 7 - THIRD PARTY LINKS</strong><br> We are not responsible for third‑party websites linked from our store. </p> <p><strong>SECTION 8 - LIABILITY</strong><br> SummitCamp is not liable for damages resulting from the use of this website. </p> <p><strong>SECTION 9 - CONTACT</strong><br> Questions about the Terms of Service should be sent to:<br> contact@podcrewshop.com </p> <hr> | I9: =SUBSTITUTE(SUBSTITUTE(SUBSTITUTE(SUBSTITUTE(SUBSTITUTE(Templates!$B$5,"{{STORE}}",$A9),"{{EMAIL}}",$B9),"{{DOMAIN}}",IF(C9<>"",C9,IFERROR(MID(B9,FIND("@",B9)+1,255),""))),"{{LAST_UPDATED}}",$E9),"{{ADDRESS_TEXT}}",IF(D9<>"",D9,"[Add mailing address]")) -> <p><strong>Last updated:</strong> March 12, 2026</p> <p> SummitCamp operates this website and collects certain personal information to provide services. </p> <h2>Information We Collect</h2> <ul> <li>Name</li> <li>Email</li> <li>Shipping address</li> <li>Billing address</li> <li>Payment details</li> <li>Device information</li> </ul> <h2>How We Use Information</h2> <ul> <li>Process orders</li> <li>Provide support</li> <li>Improve the store</li> <li>Prevent fraud</li> </ul> <h2>Sharing Information</h2> <p> We may share information with Shopify, payment providers, and shipping partners to fulfill orders. </p> <h2>Cookies</h2> <p> Cookies are used to improve user experience and analyze website traffic. </p> <h2>Your Rights</h2> <p> You may request access, correction, or deletion of your personal information. </p> <h2>Security</h2> <p> We implement security measures to protect your data but cannot guarantee absolute security. </p> <h2>Contact</h2> <p> For privacy questions contact:<br> contact@podcrewshop.com </p>
A10: PineRidge | B10: contact@podcrewshop.com | E10: March 12, 2026 | F10: =SUBSTITUTE(SUBSTITUTE(Templates!$B$2,"{{STORE}}",$A10),"{{EMAIL}}",$B10) -> <h4 style="text-align: center;">Refund, Replacement &amp; Cancellation Policy</h4> <p>At PineRidge, each product is made to order and produced specifically for you after the order is placed. Because of this, we maintain a strict but fair refund and replacement policy.</p> <p><strong>1. Order Cancellation</strong></p> <p>Orders may be cancelled <strong>within 6 hours of placing the order.</strong><br>After this period, the order may already be in production and cannot be cancelled or modified.<br>To request a cancellation, please contact us immediately at: contact@podcrewshop.com</p> <p>Requests submitted after the 6-hour cancellation window cannot be guaranteed as the order may already be in production.</p> <p>If a cancellation request is approved within the allowed time window, a 30% management, processing, and transaction fee will be deducted from the total order value.<br>This fee covers costs that are non-recoverable once the order is placed, including but not limited to:<br>- Payment processing and transaction fees<br>- Order processing and administrative costs<br>- Production preparation and fulfillment system allocation<br>The remaining balance will be refunded to the original payment method.</p> <p><strong>2. Defective, Damaged, or Incorrect Items</strong></p> <p>If you receive an item that is <strong>defective, damaged during shipping, or incorrect</strong>, please contact us within <strong>72 hours after delivery confirmation.</strong><br>Your email must include:<br>- Your order number<br>- <strong>Clear photos</strong> of the product and the issue<br>- A brief description of the problem</p> <p>Please send your request to: contact@podcrewshop.com</p> <p>After review and approval, we will <strong>either</strong>:<br>- Send a <strong>free replacement</strong>, or<br>- Issue a <strong>full refund</strong></p> <p>We may request additional photos or information to verify the issue.<br>In some cases, we may request the defective item to be returned before processing the resolution.</p> <p><strong>3. Custom &amp; Made-To-Order Products</strong></p> <p>All products sold on PineRidge are <strong>custom-made or printed on demand.</strong><br>Because these products are made specifically for each order, <strong>we do not accept returns or refunds for the following reasons:</strong><br>- Incorrect size ordered<br>- Change of mind<br>- Incorrect shipping address provided by the customer<br>- Minor color differences due to screen display<br>- Custom name or personalization errors provided by the customer</p> <p>However, we understand mistakes happen. As a courtesy, we may offer <strong>a replacement with a 50% discount</strong> if you wish to reorder the correct size, color, or product.</p> <p><strong>4. Refund Processing</strong></p> <p>If your refund request is approved, refunds will be processed to your <strong>original payment method.</strong><br>Please allow <strong>5–7 business days</strong> for the refund to appear in your account depending on your bank or payment provider.<br>Once a refund has been issued, we will send a <strong>confirmation email.</strong></p> <p><strong>5. Late or Missing Refunds</strong></p> <p>If you have not received your refund:<br>- Check your bank account again.<br>- Contact your credit card company or payment provider.<br>- Contact your bank.</p> <p>Refunds can take several business days to process depending on your financial institution.<br>If 10 business days have passed since the refund confirmation and you still have not received the funds, please contact us at: contact@podcrewshop.com</p> <p><strong>6. Chargebacks &amp; Payment Disputes</strong></p> <p>If a chargeback or payment dispute is opened without contacting our support team first, we reserve the right to submit all order information, delivery confirmation, and communication records to the payment provider.<br>We are always happy to resolve any issues directly with our customers and encourage contacting us first for the fastest resolution.</p> | G10: =SUBSTITUTE(SUBSTITUTE(Templates!$B$3,"{{STORE}}",$A10),"{{EMAIL}}",$B10) -> <p><strong>Production Time</strong></p> <p>All products at PineRidge are made-to-order and produced specifically according to your selected design, size, and color. We do not keep inventory, which means each item is manufactured after your order is placed.<br>Production typically takes 5–10 business days (excluding weekends and holidays) before the order is shipped.<br>Orders enter the production process within 6 hours after being placed. Once production has started, orders cannot be modified or canceled.</p> <p><strong>Shipping Time</strong></p> <p>After production is completed, your order will be shipped according to the shipping method selected at checkout.</p> <p>Estimated delivery times:<br>Standard Shipping: 10–20 business days<br>Fast Shipping: 5–10 business days</p> <p>Delivery times may vary depending on your location, customs processing, and carrier delays.<br>Once your order has been shipped, you will receive a tracking number via email.</p> <p><strong>Estimated Delivery Time</strong></p> <p>Total estimated delivery time includes production time + shipping time.<br>Example:<br>- Standard Shipping: 15–30 business days total<br>- Fast Shipping: 10–20 business days total</p> <p>For the most accurate estimate, please check the estimated delivery date on your order confirmation email.<br>If you have any questions about your order, please contact us at: contact@podcrewshop.com</p> <p><strong>Shipping Cost</strong></p> <p>- $5.95 for orders under $90<br>- Free shipping for orders $90 and above</p> <p><strong>PineRidge is not responsible for delays caused by carriers, customs clearance, weather conditions, or peak holiday seasons.</strong></p> | H10: =SUBSTITUTE(SUBSTITUTE(SUBSTITUTE(SUBSTITUTE(SUBSTITUTE(Templates!$B$4,"{{STORE}}",$A10),"{{EMAIL}}",$B10),"{{DOMAIN}}",IF(C10<>"",C10,IFERROR(MID(B10,FIND("@",B10)+1,255),""))),"{{LAST_UPDATED}}",$E10),"{{ADDRESS_TEXT}}",IF(D10<>"",D10,"[Add mailing address]")) -> <p><strong>OVERVIEW</strong><br> Welcome to PineRidge! The terms “we”, “us” and “our” refer to PineRidge. PineRidge operates this store and website, including all related information, content, features, tools, products and services in order to provide you with a shopping experience. PineRidge is powered by Shopify. </p> <p>By visiting or using our Services, you agree to these Terms of Service.</p> <p><strong>SECTION 1 - ACCESS</strong><br> You must be at least the age of majority in your jurisdiction to use this website. </p> <p><strong>SECTION 2 - PRODUCTS</strong><br> Product colors may appear differently depending on your device display. </p> <p><strong>SECTION 3 - ORDERS</strong><br> We reserve the right to refuse or cancel orders at our discretion. </p> <p><strong>SECTION 4 - PRICES</strong><br> Prices may change without notice. </p> <p><strong>SECTION 5 - SHIPPING</strong><br> Delivery times are estimates only. </p> <p><strong>SECTION 6 - INTELLECTUAL PROPERTY</strong><br> All website content belongs to PineRidge or its licensors. </p> <p><strong>SECTION 7 - THIRD PARTY LINKS</strong><br> We are not responsible for third‑party websites linked from our store. </p> <p><strong>SECTION 8 - LIABILITY</strong><br> PineRidge is not liable for damages resulting from the use of this website. </p> <p><strong>SECTION 9 - CONTACT</strong><br> Questions about the Terms of Service should be sent to:<br> contact@podcrewshop.com </p> <hr> | I10: =SUBSTITUTE(SUBSTITUTE(SUBSTITUTE(SUBSTITUTE(SUBSTITUTE(Templates!$B$5,"{{STORE}}",$A10),"{{EMAIL}}",$B10),"{{DOMAIN}}",IF(C10<>"",C10,IFERROR(MID(B10,FIND("@",B10)+1,255),""))),"{{LAST_UPDATED}}",$E10),"{{ADDRESS_TEXT}}",IF(D10<>"",D10,"[Add mailing address]")) -> <p><strong>Last updated:</strong> March 12, 2026</p> <p> PineRidge operates this website and collects certain personal information to provide services. </p> <h2>Information We Collect</h2> <ul> <li>Name</li> <li>Email</li> <li>Shipping address</li> <li>Billing address</li> <li>Payment details</li> <li>Device information</li> </ul> <h2>How We Use Information</h2> <ul> <li>Process orders</li> <li>Provide support</li> <li>Improve the store</li> <li>Prevent fraud</li> </ul> <h2>Sharing Information</h2> <p> We may share information with Shopify, payment providers, and shipping partners to fulfill orders. </p> <h2>Cookies</h2> <p> Cookies are used to improve user experience and analyze website traffic. </p> <h2>Your Rights</h2> <p> You may request access, correction, or deletion of your personal information. </p> <h2>Security</h2> <p> We implement security measures to protect your data but cannot guarantee absolute security. </p> <h2>Contact</h2> <p> For privacy questions contact:<br> contact@podcrewshop.com </p>
A11: TimberTrail | B11: contact@podcrewshop.com | E11: March 12, 2026 | F11: =SUBSTITUTE(SUBSTITUTE(Templates!$B$2,"{{STORE}}",$A11),"{{EMAIL}}",$B11) -> <h4 style="text-align: center;">Refund, Replacement &amp; Cancellation Policy</h4> <p>At TimberTrail, each product is made to order and produced specifically for you after the order is placed. Because of this, we maintain a strict but fair refund and replacement policy.</p> <p><strong>1. Order Cancellation</strong></p> <p>Orders may be cancelled <strong>within 6 hours of placing the order.</strong><br>After this period, the order may already be in production and cannot be cancelled or modified.<br>To request a cancellation, please contact us immediately at: contact@podcrewshop.com</p> <p>Requests submitted after the 6-hour cancellation window cannot be guaranteed as the order may already be in production.</p> <p>If a cancellation request is approved within the allowed time window, a 30% management, processing, and transaction fee will be deducted from the total order value.<br>This fee covers costs that are non-recoverable once the order is placed, including but not limited to:<br>- Payment processing and transaction fees<br>- Order processing and administrative costs<br>- Production preparation and fulfillment system allocation<br>The remaining balance will be refunded to the original payment method.</p> <p><strong>2. Defective, Damaged, or Incorrect Items</strong></p> <p>If you receive an item that is <strong>defective, damaged during shipping, or incorrect</strong>, please contact us within <strong>72 hours after delivery confirmation.</strong><br>Your email must include:<br>- Your order number<br>- <strong>Clear photos</strong> of the product and the issue<br>- A brief description of the problem</p> <p>Please send your request to: contact@podcrewshop.com</p> <p>After review and approval, we will <strong>either</strong>:<br>- Send a <strong>free replacement</strong>, or<br>- Issue a <strong>full refund</strong></p> <p>We may request additional photos or information to verify the issue.<br>In some cases, we may request the defective item to be returned before processing the resolution.</p> <p><strong>3. Custom &amp; Made-To-Order Products</strong></p> <p>All products sold on TimberTrail are <strong>custom-made or printed on demand.</strong><br>Because these products are made specifically for each order, <strong>we do not accept returns or refunds for the following reasons:</strong><br>- Incorrect size ordered<br>- Change of mind<br>- Incorrect shipping address provided by the customer<br>- Minor color differences due to screen display<br>- Custom name or personalization errors provided by the customer</p> <p>However, we understand mistakes happen. As a courtesy, we may offer <strong>a replacement with a 50% discount</strong> if you wish to reorder the correct size, color, or product.</p> <p><strong>4. Refund Processing</strong></p> <p>If your refund request is approved, refunds will be processed to your <strong>original payment method.</strong><br>Please allow <strong>5–7 business days</strong> for the refund to appear in your account depending on your bank or payment provider.<br>Once a refund has been issued, we will send a <strong>confirmation email.</strong></p> <p><strong>5. Late or Missing Refunds</strong></p> <p>If you have not received your refund:<br>- Check your bank account again.<br>- Contact your credit card company or payment provider.<br>- Contact your bank.</p> <p>Refunds can take several business days to process depending on your financial institution.<br>If 10 business days have passed since the refund confirmation and you still have not received the funds, please contact us at: contact@podcrewshop.com</p> <p><strong>6. Chargebacks &amp; Payment Disputes</strong></p> <p>If a chargeback or payment dispute is opened without contacting our support team first, we reserve the right to submit all order information, delivery confirmation, and communication records to the payment provider.<br>We are always happy to resolve any issues directly with our customers and encourage contacting us first for the fastest resolution.</p> | G11: =SUBSTITUTE(SUBSTITUTE(Templates!$B$3,"{{STORE}}",$A11),"{{EMAIL}}",$B11) -> <p><strong>Production Time</strong></p> <p>All products at TimberTrail are made-to-order and produced specifically according to your selected design, size, and color. We do not keep inventory, which means each item is manufactured after your order is placed.<br>Production typically takes 5–10 business days (excluding weekends and holidays) before the order is shipped.<br>Orders enter the production process within 6 hours after being placed. Once production has started, orders cannot be modified or canceled.</p> <p><strong>Shipping Time</strong></p> <p>After production is completed, your order will be shipped according to the shipping method selected at checkout.</p> <p>Estimated delivery times:<br>Standard Shipping: 10–20 business days<br>Fast Shipping: 5–10 business days</p> <p>Delivery times may vary depending on your location, customs processing, and carrier delays.<br>Once your order has been shipped, you will receive a tracking number via email.</p> <p><strong>Estimated Delivery Time</strong></p> <p>Total estimated delivery time includes production time + shipping time.<br>Example:<br>- Standard Shipping: 15–30 business days total<br>- Fast Shipping: 10–20 business days total</p> <p>For the most accurate estimate, please check the estimated delivery date on your order confirmation email.<br>If you have any questions about your order, please contact us at: contact@podcrewshop.com</p> <p><strong>Shipping Cost</strong></p> <p>- $5.95 for orders under $90<br>- Free shipping for orders $90 and above</p> <p><strong>TimberTrail is not responsible for delays caused by carriers, customs clearance, weather conditions, or peak holiday seasons.</strong></p> | H11: =SUBSTITUTE(SUBSTITUTE(SUBSTITUTE(SUBSTITUTE(SUBSTITUTE(Templates!$B$4,"{{STORE}}",$A11),"{{EMAIL}}",$B11),"{{DOMAIN}}",IF(C11<>"",C11,IFERROR(MID(B11,FIND("@",B11)+1,255),""))),"{{LAST_UPDATED}}",$E11),"{{ADDRESS_TEXT}}",IF(D11<>"",D11,"[Add mailing address]")) -> <p><strong>OVERVIEW</strong><br> Welcome to TimberTrail! The terms “we”, “us” and “our” refer to TimberTrail. TimberTrail operates this store and website, including all related information, content, features, tools, products and services in order to provide you with a shopping experience. TimberTrail is powered by Shopify. </p> <p>By visiting or using our Services, you agree to these Terms of Service.</p> <p><strong>SECTION 1 - ACCESS</strong><br> You must be at least the age of majority in your jurisdiction to use this website. </p> <p><strong>SECTION 2 - PRODUCTS</strong><br> Product colors may appear differently depending on your device display. </p> <p><strong>SECTION 3 - ORDERS</strong><br> We reserve the right to refuse or cancel orders at our discretion. </p> <p><strong>SECTION 4 - PRICES</strong><br> Prices may change without notice. </p> <p><strong>SECTION 5 - SHIPPING</strong><br> Delivery times are estimates only. </p> <p><strong>SECTION 6 - INTELLECTUAL PROPERTY</strong><br> All website content belongs to TimberTrail or its licensors. </p> <p><strong>SECTION 7 - THIRD PARTY LINKS</strong><br> We are not responsible for third‑party websites linked from our store. </p> <p><strong>SECTION 8 - LIABILITY</strong><br> TimberTrail is not liable for damages resulting from the use of this website. </p> <p><strong>SECTION 9 - CONTACT</strong><br> Questions about the Terms of Service should be sent to:<br> contact@podcrewshop.com </p> <hr> | I11: =SUBSTITUTE(SUBSTITUTE(SUBSTITUTE(SUBSTITUTE(SUBSTITUTE(Templates!$B$5,"{{STORE}}",$A11),"{{EMAIL}}",$B11),"{{DOMAIN}}",IF(C11<>"",C11,IFERROR(MID(B11,FIND("@",B11)+1,255),""))),"{{LAST_UPDATED}}",$E11),"{{ADDRESS_TEXT}}",IF(D11<>"",D11,"[Add mailing address]")) -> <p><strong>Last updated:</strong> March 12, 2026</p> <p> TimberTrail operates this website and collects certain personal information to provide services. </p> <h2>Information We Collect</h2> <ul> <li>Name</li> <li>Email</li> <li>Shipping address</li> <li>Billing address</li> <li>Payment details</li> <li>Device information</li> </ul> <h2>How We Use Information</h2> <ul> <li>Process orders</li> <li>Provide support</li> <li>Improve the store</li> <li>Prevent fraud</li> </ul> <h2>Sharing Information</h2> <p> We may share information with Shopify, payment providers, and shipping partners to fulfill orders. </p> <h2>Cookies</h2> <p> Cookies are used to improve user experience and analyze website traffic. </p> <h2>Your Rights</h2> <p> You may request access, correction, or deletion of your personal information. </p> <h2>Security</h2> <p> We implement security measures to protect your data but cannot guarantee absolute security. </p> <h2>Contact</h2> <p> For privacy questions contact:<br> contact@podcrewshop.com </p>
A12: WildCamp | B12: contact@podcrewshop.com | E12: March 12, 2026 | F12: =SUBSTITUTE(SUBSTITUTE(Templates!$B$2,"{{STORE}}",$A12),"{{EMAIL}}",$B12) -> <h4 style="text-align: center;">Refund, Replacement &amp; Cancellation Policy</h4> <p>At WildCamp, each product is made to order and produced specifically for you after the order is placed. Because of this, we maintain a strict but fair refund and replacement policy.</p> <p><strong>1. Order Cancellation</strong></p> <p>Orders may be cancelled <strong>within 6 hours of placing the order.</strong><br>After this period, the order may already be in production and cannot be cancelled or modified.<br>To request a cancellation, please contact us immediately at: contact@podcrewshop.com</p> <p>Requests submitted after the 6-hour cancellation window cannot be guaranteed as the order may already be in production.</p> <p>If a cancellation request is approved within the allowed time window, a 30% management, processing, and transaction fee will be deducted from the total order value.<br>This fee covers costs that are non-recoverable once the order is placed, including but not limited to:<br>- Payment processing and transaction fees<br>- Order processing and administrative costs<br>- Production preparation and fulfillment system allocation<br>The remaining balance will be refunded to the original payment method.</p> <p><strong>2. Defective, Damaged, or Incorrect Items</strong></p> <p>If you receive an item that is <strong>defective, damaged during shipping, or incorrect</strong>, please contact us within <strong>72 hours after delivery confirmation.</strong><br>Your email must include:<br>- Your order number<br>- <strong>Clear photos</strong> of the product and the issue<br>- A brief description of the problem</p> <p>Please send your request to: contact@podcrewshop.com</p> <p>After review and approval, we will <strong>either</strong>:<br>- Send a <strong>free replacement</strong>, or<br>- Issue a <strong>full refund</strong></p> <p>We may request additional photos or information to verify the issue.<br>In some cases, we may request the defective item to be returned before processing the resolution.</p> <p><strong>3. Custom &amp; Made-To-Order Products</strong></p> <p>All products sold on WildCamp are <strong>custom-made or printed on demand.</strong><br>Because these products are made specifically for each order, <strong>we do not accept returns or refunds for the following reasons:</strong><br>- Incorrect size ordered<br>- Change of mind<br>- Incorrect shipping address provided by the customer<br>- Minor color differences due to screen display<br>- Custom name or personalization errors provided by the customer</p> <p>However, we understand mistakes happen. As a courtesy, we may offer <strong>a replacement with a 50% discount</strong> if you wish to reorder the correct size, color, or product.</p> <p><strong>4. Refund Processing</strong></p> <p>If your refund request is approved, refunds will be processed to your <strong>original payment method.</strong><br>Please allow <strong>5–7 business days</strong> for the refund to appear in your account depending on your bank or payment provider.<br>Once a refund has been issued, we will send a <strong>confirmation email.</strong></p> <p><strong>5. Late or Missing Refunds</strong></p> <p>If you have not received your refund:<br>- Check your bank account again.<br>- Contact your credit card company or payment provider.<br>- Contact your bank.</p> <p>Refunds can take several business days to process depending on your financial institution.<br>If 10 business days have passed since the refund confirmation and you still have not received the funds, please contact us at: contact@podcrewshop.com</p> <p><strong>6. Chargebacks &amp; Payment Disputes</strong></p> <p>If a chargeback or payment dispute is opened without contacting our support team first, we reserve the right to submit all order information, delivery confirmation, and communication records to the payment provider.<br>We are always happy to resolve any issues directly with our customers and encourage contacting us first for the fastest resolution.</p> | G12: =SUBSTITUTE(SUBSTITUTE(Templates!$B$3,"{{STORE}}",$A12),"{{EMAIL}}",$B12) -> <p><strong>Production Time</strong></p> <p>All products at WildCamp are made-to-order and produced specifically according to your selected design, size, and color. We do not keep inventory, which means each item is manufactured after your order is placed.<br>Production typically takes 5–10 business days (excluding weekends and holidays) before the order is shipped.<br>Orders enter the production process within 6 hours after being placed. Once production has started, orders cannot be modified or canceled.</p> <p><strong>Shipping Time</strong></p> <p>After production is completed, your order will be shipped according to the shipping method selected at checkout.</p> <p>Estimated delivery times:<br>Standard Shipping: 10–20 business days<br>Fast Shipping: 5–10 business days</p> <p>Delivery times may vary depending on your location, customs processing, and carrier delays.<br>Once your order has been shipped, you will receive a tracking number via email.</p> <p><strong>Estimated Delivery Time</strong></p> <p>Total estimated delivery time includes production time + shipping time.<br>Example:<br>- Standard Shipping: 15–30 business days total<br>- Fast Shipping: 10–20 business days total</p> <p>For the most accurate estimate, please check the estimated delivery date on your order confirmation email.<br>If you have any questions about your order, please contact us at: contact@podcrewshop.com</p> <p><strong>Shipping Cost</strong></p> <p>- $5.95 for orders under $90<br>- Free shipping for orders $90 and above</p> <p><strong>WildCamp is not responsible for delays caused by carriers, customs clearance, weather conditions, or peak holiday seasons.</strong></p> | H12: =SUBSTITUTE(SUBSTITUTE(SUBSTITUTE(SUBSTITUTE(SUBSTITUTE(Templates!$B$4,"{{STORE}}",$A12),"{{EMAIL}}",$B12),"{{DOMAIN}}",IF(C12<>"",C12,IFERROR(MID(B12,FIND("@",B12)+1,255),""))),"{{LAST_UPDATED}}",$E12),"{{ADDRESS_TEXT}}",IF(D12<>"",D12,"[Add mailing address]")) -> <p><strong>OVERVIEW</strong><br> Welcome to WildCamp! The terms “we”, “us” and “our” refer to WildCamp. WildCamp operates this store and website, including all related information, content, features, tools, products and services in order to provide you with a shopping experience. WildCamp is powered by Shopify. </p> <p>By visiting or using our Services, you agree to these Terms of Service.</p> <p><strong>SECTION 1 - ACCESS</strong><br> You must be at least the age of majority in your jurisdiction to use this website. </p> <p><strong>SECTION 2 - PRODUCTS</strong><br> Product colors may appear differently depending on your device display. </p> <p><strong>SECTION 3 - ORDERS</strong><br> We reserve the right to refuse or cancel orders at our discretion. </p> <p><strong>SECTION 4 - PRICES</strong><br> Prices may change without notice. </p> <p><strong>SECTION 5 - SHIPPING</strong><br> Delivery times are estimates only. </p> <p><strong>SECTION 6 - INTELLECTUAL PROPERTY</strong><br> All website content belongs to WildCamp or its licensors. </p> <p><strong>SECTION 7 - THIRD PARTY LINKS</strong><br> We are not responsible for third‑party websites linked from our store. </p> <p><strong>SECTION 8 - LIABILITY</strong><br> WildCamp is not liable for damages resulting from the use of this website. </p> <p><strong>SECTION 9 - CONTACT</strong><br> Questions about the Terms of Service should be sent to:<br> contact@podcrewshop.com </p> <hr> | I12: =SUBSTITUTE(SUBSTITUTE(SUBSTITUTE(SUBSTITUTE(SUBSTITUTE(Templates!$B$5,"{{STORE}}",$A12),"{{EMAIL}}",$B12),"{{DOMAIN}}",IF(C12<>"",C12,IFERROR(MID(B12,FIND("@",B12)+1,255),""))),"{{LAST_UPDATED}}",$E12),"{{ADDRESS_TEXT}}",IF(D12<>"",D12,"[Add mailing address]")) -> <p><strong>Last updated:</strong> March 12, 2026</p> <p> WildCamp operates this website and collects certain personal information to provide services. </p> <h2>Information We Collect</h2> <ul> <li>Name</li> <li>Email</li> <li>Shipping address</li> <li>Billing address</li> <li>Payment details</li> <li>Device information</li> </ul> <h2>How We Use Information</h2> <ul> <li>Process orders</li> <li>Provide support</li> <li>Improve the store</li> <li>Prevent fraud</li> </ul> <h2>Sharing Information</h2> <p> We may share information with Shopify, payment providers, and shipping partners to fulfill orders. </p> <h2>Cookies</h2> <p> Cookies are used to improve user experience and analyze website traffic. </p> <h2>Your Rights</h2> <p> You may request access, correction, or deletion of your personal information. </p> <h2>Security</h2> <p> We implement security measures to protect your data but cannot guarantee absolute security. </p> <h2>Contact</h2> <p> For privacy questions contact:<br> contact@podcrewshop.com </p>
A13: Frontier | B13: contact@podcrewshop.com | E13: March 12, 2026 | F13: =SUBSTITUTE(SUBSTITUTE(Templates!$B$2,"{{STORE}}",$A13),"{{EMAIL}}",$B13) -> <h4 style="text-align: center;">Refund, Replacement &amp; Cancellation Policy</h4> <p>At Frontier, each product is made to order and produced specifically for you after the order is placed. Because of this, we maintain a strict but fair refund and replacement policy.</p> <p><strong>1. Order Cancellation</strong></p> <p>Orders may be cancelled <strong>within 6 hours of placing the order.</strong><br>After this period, the order may already be in production and cannot be cancelled or modified.<br>To request a cancellation, please contact us immediately at: contact@podcrewshop.com</p> <p>Requests submitted after the 6-hour cancellation window cannot be guaranteed as the order may already be in production.</p> <p>If a cancellation request is approved within the allowed time window, a 30% management, processing, and transaction fee will be deducted from the total order value.<br>This fee covers costs that are non-recoverable once the order is placed, including but not limited to:<br>- Payment processing and transaction fees<br>- Order processing and administrative costs<br>- Production preparation and fulfillment system allocation<br>The remaining balance will be refunded to the original payment method.</p> <p><strong>2. Defective, Damaged, or Incorrect Items</strong></p> <p>If you receive an item that is <strong>defective, damaged during shipping, or incorrect</strong>, please contact us within <strong>72 hours after delivery confirmation.</strong><br>Your email must include:<br>- Your order number<br>- <strong>Clear photos</strong> of the product and the issue<br>- A brief description of the problem</p> <p>Please send your request to: contact@podcrewshop.com</p> <p>After review and approval, we will <strong>either</strong>:<br>- Send a <strong>free replacement</strong>, or<br>- Issue a <strong>full refund</strong></p> <p>We may request additional photos or information to verify the issue.<br>In some cases, we may request the defective item to be returned before processing the resolution.</p> <p><strong>3. Custom &amp; Made-To-Order Products</strong></p> <p>All products sold on Frontier are <strong>custom-made or printed on demand.</strong><br>Because these products are made specifically for each order, <strong>we do not accept returns or refunds for the following reasons:</strong><br>- Incorrect size ordered<br>- Change of mind<br>- Incorrect shipping address provided by the customer<br>- Minor color differences due to screen display<br>- Custom name or personalization errors provided by the customer</p> <p>However, we understand mistakes happen. As a courtesy, we may offer <strong>a replacement with a 50% discount</strong> if you wish to reorder the correct size, color, or product.</p> <p><strong>4. Refund Processing</strong></p> <p>If your refund request is approved, refunds will be processed to your <strong>original payment method.</strong><br>Please allow <strong>5–7 business days</strong> for the refund to appear in your account depending on your bank or payment provider.<br>Once a refund has been issued, we will send a <strong>confirmation email.</strong></p> <p><strong>5. Late or Missing Refunds</strong></p> <p>If you have not received your refund:<br>- Check your bank account again.<br>- Contact your credit card company or payment provider.<br>- Contact your bank.</p> <p>Refunds can take several business days to process depending on your financial institution.<br>If 10 business days have passed since the refund confirmation and you still have not received the funds, please contact us at: contact@podcrewshop.com</p> <p><strong>6. Chargebacks &amp; Payment Disputes</strong></p> <p>If a chargeback or payment dispute is opened without contacting our support team first, we reserve the right to submit all order information, delivery confirmation, and communication records to the payment provider.<br>We are always happy to resolve any issues directly with our customers and encourage contacting us first for the fastest resolution.</p> | G13: =SUBSTITUTE(SUBSTITUTE(Templates!$B$3,"{{STORE}}",$A13),"{{EMAIL}}",$B13) -> <p><strong>Production Time</strong></p> <p>All products at Frontier are made-to-order and produced specifically according to your selected design, size, and color. We do not keep inventory, which means each item is manufactured after your order is placed.<br>Production typically takes 5–10 business days (excluding weekends and holidays) before the order is shipped.<br>Orders enter the production process within 6 hours after being placed. Once production has started, orders cannot be modified or canceled.</p> <p><strong>Shipping Time</strong></p> <p>After production is completed, your order will be shipped according to the shipping method selected at checkout.</p> <p>Estimated delivery times:<br>Standard Shipping: 10–20 business days<br>Fast Shipping: 5–10 business days</p> <p>Delivery times may vary depending on your location, customs processing, and carrier delays.<br>Once your order has been shipped, you will receive a tracking number via email.</p> <p><strong>Estimated Delivery Time</strong></p> <p>Total estimated delivery time includes production time + shipping time.<br>Example:<br>- Standard Shipping: 15–30 business days total<br>- Fast Shipping: 10–20 business days total</p> <p>For the most accurate estimate, please check the estimated delivery date on your order confirmation email.<br>If you have any questions about your order, please contact us at: contact@podcrewshop.com</p> <p><strong>Shipping Cost</strong></p> <p>- $5.95 for orders under $90<br>- Free shipping for orders $90 and above</p> <p><strong>Frontier is not responsible for delays caused by carriers, customs clearance, weather conditions, or peak holiday seasons.</strong></p> | H13: =SUBSTITUTE(SUBSTITUTE(SUBSTITUTE(SUBSTITUTE(SUBSTITUTE(Templates!$B$4,"{{STORE}}",$A13),"{{EMAIL}}",$B13),"{{DOMAIN}}",IF(C13<>"",C13,IFERROR(MID(B13,FIND("@",B13)+1,255),""))),"{{LAST_UPDATED}}",$E13),"{{ADDRESS_TEXT}}",IF(D13<>"",D13,"[Add mailing address]")) -> <p><strong>OVERVIEW</strong><br> Welcome to Frontier! The terms “we”, “us” and “our” refer to Frontier. Frontier operates this store and website, including all related information, content, features, tools, products and services in order to provide you with a shopping experience. Frontier is powered by Shopify. </p> <p>By visiting or using our Services, you agree to these Terms of Service.</p> <p><strong>SECTION 1 - ACCESS</strong><br> You must be at least the age of majority in your jurisdiction to use this website. </p> <p><strong>SECTION 2 - PRODUCTS</strong><br> Product colors may appear differently depending on your device display. </p> <p><strong>SECTION 3 - ORDERS</strong><br> We reserve the right to refuse or cancel orders at our discretion. </p> <p><strong>SECTION 4 - PRICES</strong><br> Prices may change without notice. </p> <p><strong>SECTION 5 - SHIPPING</strong><br> Delivery times are estimates only. </p> <p><strong>SECTION 6 - INTELLECTUAL PROPERTY</strong><br> All website content belongs to Frontier or its licensors. </p> <p><strong>SECTION 7 - THIRD PARTY LINKS</strong><br> We are not responsible for third‑party websites linked from our store. </p> <p><strong>SECTION 8 - LIABILITY</strong><br> Frontier is not liable for damages resulting from the use of this website. </p> <p><strong>SECTION 9 - CONTACT</strong><br> Questions about the Terms of Service should be sent to:<br> contact@podcrewshop.com </p> <hr> | I13: =SUBSTITUTE(SUBSTITUTE(SUBSTITUTE(SUBSTITUTE(SUBSTITUTE(Templates!$B$5,"{{STORE}}",$A13),"{{EMAIL}}",$B13),"{{DOMAIN}}",IF(C13<>"",C13,IFERROR(MID(B13,FIND("@",B13)+1,255),""))),"{{LAST_UPDATED}}",$E13),"{{ADDRESS_TEXT}}",IF(D13<>"",D13,"[Add mailing address]")) -> <p><strong>Last updated:</strong> March 12, 2026</p> <p> Frontier operates this website and collects certain personal information to provide services. </p> <h2>Information We Collect</h2> <ul> <li>Name</li> <li>Email</li> <li>Shipping address</li> <li>Billing address</li> <li>Payment details</li> <li>Device information</li> </ul> <h2>How We Use Information</h2> <ul> <li>Process orders</li> <li>Provide support</li> <li>Improve the store</li> <li>Prevent fraud</li> </ul> <h2>Sharing Information</h2> <p> We may share information with Shopify, payment providers, and shipping partners to fulfill orders. </p> <h2>Cookies</h2> <p> Cookies are used to improve user experience and analyze website traffic. </p> <h2>Your Rights</h2> <p> You may request access, correction, or deletion of your personal information. </p> <h2>Security</h2> <p> We implement security measures to protect your data but cannot guarantee absolute security. </p> <h2>Contact</h2> <p> For privacy questions contact:<br> contact@podcrewshop.com </p>
A14: IronTrail | B14: contact@podcrewshop.com | E14: March 12, 2026 | F14: =SUBSTITUTE(SUBSTITUTE(Templates!$B$2,"{{STORE}}",$A14),"{{EMAIL}}",$B14) -> <h4 style="text-align: center;">Refund, Replacement &amp; Cancellation Policy</h4> <p>At IronTrail, each product is made to order and produced specifically for you after the order is placed. Because of this, we maintain a strict but fair refund and replacement policy.</p> <p><strong>1. Order Cancellation</strong></p> <p>Orders may be cancelled <strong>within 6 hours of placing the order.</strong><br>After this period, the order may already be in production and cannot be cancelled or modified.<br>To request a cancellation, please contact us immediately at: contact@podcrewshop.com</p> <p>Requests submitted after the 6-hour cancellation window cannot be guaranteed as the order may already be in production.</p> <p>If a cancellation request is approved within the allowed time window, a 30% management, processing, and transaction fee will be deducted from the total order value.<br>This fee covers costs that are non-recoverable once the order is placed, including but not limited to:<br>- Payment processing and transaction fees<br>- Order processing and administrative costs<br>- Production preparation and fulfillment system allocation<br>The remaining balance will be refunded to the original payment method.</p> <p><strong>2. Defective, Damaged, or Incorrect Items</strong></p> <p>If you receive an item that is <strong>defective, damaged during shipping, or incorrect</strong>, please contact us within <strong>72 hours after delivery confirmation.</strong><br>Your email must include:<br>- Your order number<br>- <strong>Clear photos</strong> of the product and the issue<br>- A brief description of the problem</p> <p>Please send your request to: contact@podcrewshop.com</p> <p>After review and approval, we will <strong>either</strong>:<br>- Send a <strong>free replacement</strong>, or<br>- Issue a <strong>full refund</strong></p> <p>We may request additional photos or information to verify the issue.<br>In some cases, we may request the defective item to be returned before processing the resolution.</p> <p><strong>3. Custom &amp; Made-To-Order Products</strong></p> <p>All products sold on IronTrail are <strong>custom-made or printed on demand.</strong><br>Because these products are made specifically for each order, <strong>we do not accept returns or refunds for the following reasons:</strong><br>- Incorrect size ordered<br>- Change of mind<br>- Incorrect shipping address provided by the customer<br>- Minor color differences due to screen display<br>- Custom name or personalization errors provided by the customer</p> <p>However, we understand mistakes happen. As a courtesy, we may offer <strong>a replacement with a 50% discount</strong> if you wish to reorder the correct size, color, or product.</p> <p><strong>4. Refund Processing</strong></p> <p>If your refund request is approved, refunds will be processed to your <strong>original payment method.</strong><br>Please allow <strong>5–7 business days</strong> for the refund to appear in your account depending on your bank or payment provider.<br>Once a refund has been issued, we will send a <strong>confirmation email.</strong></p> <p><strong>5. Late or Missing Refunds</strong></p> <p>If you have not received your refund:<br>- Check your bank account again.<br>- Contact your credit card company or payment provider.<br>- Contact your bank.</p> <p>Refunds can take several business days to process depending on your financial institution.<br>If 10 business days have passed since the refund confirmation and you still have not received the funds, please contact us at: contact@podcrewshop.com</p> <p><strong>6. Chargebacks &amp; Payment Disputes</strong></p> <p>If a chargeback or payment dispute is opened without contacting our support team first, we reserve the right to submit all order information, delivery confirmation, and communication records to the payment provider.<br>We are always happy to resolve any issues directly with our customers and encourage contacting us first for the fastest resolution.</p> | G14: =SUBSTITUTE(SUBSTITUTE(Templates!$B$3,"{{STORE}}",$A14),"{{EMAIL}}",$B14) -> <p><strong>Production Time</strong></p> <p>All products at IronTrail are made-to-order and produced specifically according to your selected design, size, and color. We do not keep inventory, which means each item is manufactured after your order is placed.<br>Production typically takes 5–10 business days (excluding weekends and holidays) before the order is shipped.<br>Orders enter the production process within 6 hours after being placed. Once production has started, orders cannot be modified or canceled.</p> <p><strong>Shipping Time</strong></p> <p>After production is completed, your order will be shipped according to the shipping method selected at checkout.</p> <p>Estimated delivery times:<br>Standard Shipping: 10–20 business days<br>Fast Shipping: 5–10 business days</p> <p>Delivery times may vary depending on your location, customs processing, and carrier delays.<br>Once your order has been shipped, you will receive a tracking number via email.</p> <p><strong>Estimated Delivery Time</strong></p> <p>Total estimated delivery time includes production time + shipping time.<br>Example:<br>- Standard Shipping: 15–30 business days total<br>- Fast Shipping: 10–20 business days total</p> <p>For the most accurate estimate, please check the estimated delivery date on your order confirmation email.<br>If you have any questions about your order, please contact us at: contact@podcrewshop.com</p> <p><strong>Shipping Cost</strong></p> <p>- $5.95 for orders under $90<br>- Free shipping for orders $90 and above</p> <p><strong>IronTrail is not responsible for delays caused by carriers, customs clearance, weather conditions, or peak holiday seasons.</strong></p> | H14: =SUBSTITUTE(SUBSTITUTE(SUBSTITUTE(SUBSTITUTE(SUBSTITUTE(Templates!$B$4,"{{STORE}}",$A14),"{{EMAIL}}",$B14),"{{DOMAIN}}",IF(C14<>"",C14,IFERROR(MID(B14,FIND("@",B14)+1,255),""))),"{{LAST_UPDATED}}",$E14),"{{ADDRESS_TEXT}}",IF(D14<>"",D14,"[Add mailing address]")) -> <p><strong>OVERVIEW</strong><br> Welcome to IronTrail! The terms “we”, “us” and “our” refer to IronTrail. IronTrail operates this store and website, including all related information, content, features, tools, products and services in order to provide you with a shopping experience. IronTrail is powered by Shopify. </p> <p>By visiting or using our Services, you agree to these Terms of Service.</p> <p><strong>SECTION 1 - ACCESS</strong><br> You must be at least the age of majority in your jurisdiction to use this website. </p> <p><strong>SECTION 2 - PRODUCTS</strong><br> Product colors may appear differently depending on your device display. </p> <p><strong>SECTION 3 - ORDERS</strong><br> We reserve the right to refuse or cancel orders at our discretion. </p> <p><strong>SECTION 4 - PRICES</strong><br> Prices may change without notice. </p> <p><strong>SECTION 5 - SHIPPING</strong><br> Delivery times are estimates only. </p> <p><strong>SECTION 6 - INTELLECTUAL PROPERTY</strong><br> All website content belongs to IronTrail or its licensors. </p> <p><strong>SECTION 7 - THIRD PARTY LINKS</strong><br> We are not responsible for third‑party websites linked from our store. </p> <p><strong>SECTION 8 - LIABILITY</strong><br> IronTrail is not liable for damages resulting from the use of this website. </p> <p><strong>SECTION 9 - CONTACT</strong><br> Questions about the Terms of Service should be sent to:<br> contact@podcrewshop.com </p> <hr> | I14: =SUBSTITUTE(SUBSTITUTE(SUBSTITUTE(SUBSTITUTE(SUBSTITUTE(Templates!$B$5,"{{STORE}}",$A14),"{{EMAIL}}",$B14),"{{DOMAIN}}",IF(C14<>"",C14,IFERROR(MID(B14,FIND("@",B14)+1,255),""))),"{{LAST_UPDATED}}",$E14),"{{ADDRESS_TEXT}}",IF(D14<>"",D14,"[Add mailing address]")) -> <p><strong>Last updated:</strong> March 12, 2026</p> <p> IronTrail operates this website and collects certain personal information to provide services. </p> <h2>Information We Collect</h2> <ul> <li>Name</li> <li>Email</li> <li>Shipping address</li> <li>Billing address</li> <li>Payment details</li> <li>Device information</li> </ul> <h2>How We Use Information</h2> <ul> <li>Process orders</li> <li>Provide support</li> <li>Improve the store</li> <li>Prevent fraud</li> </ul> <h2>Sharing Information</h2> <p> We may share information with Shopify, payment providers, and shipping partners to fulfill orders. </p> <h2>Cookies</h2> <p> Cookies are used to improve user experience and analyze website traffic. </p> <h2>Your Rights</h2> <p> You may request access, correction, or deletion of your personal information. </p> <h2>Security</h2> <p> We implement security measures to protect your data but cannot guarantee absolute security. </p> <h2>Contact</h2> <p> For privacy questions contact:<br> contact@podcrewshop.com </p>
A15: NorthOak | B15: contact@podcrewshop.com | E15: March 12, 2026 | F15: =SUBSTITUTE(SUBSTITUTE(Templates!$B$2,"{{STORE}}",$A15),"{{EMAIL}}",$B15) -> <h4 style="text-align: center;">Refund, Replacement &amp; Cancellation Policy</h4> <p>At NorthOak, each product is made to order and produced specifically for you after the order is placed. Because of this, we maintain a strict but fair refund and replacement policy.</p> <p><strong>1. Order Cancellation</strong></p> <p>Orders may be cancelled <strong>within 6 hours of placing the order.</strong><br>After this period, the order may already be in production and cannot be cancelled or modified.<br>To request a cancellation, please contact us immediately at: contact@podcrewshop.com</p> <p>Requests submitted after the 6-hour cancellation window cannot be guaranteed as the order may already be in production.</p> <p>If a cancellation request is approved within the allowed time window, a 30% management, processing, and transaction fee will be deducted from the total order value.<br>This fee covers costs that are non-recoverable once the order is placed, including but not limited to:<br>- Payment processing and transaction fees<br>- Order processing and administrative costs<br>- Production preparation and fulfillment system allocation<br>The remaining balance will be refunded to the original payment method.</p> <p><strong>2. Defective, Damaged, or Incorrect Items</strong></p> <p>If you receive an item that is <strong>defective, damaged during shipping, or incorrect</strong>, please contact us within <strong>72 hours after delivery confirmation.</strong><br>Your email must include:<br>- Your order number<br>- <strong>Clear photos</strong> of the product and the issue<br>- A brief description of the problem</p> <p>Please send your request to: contact@podcrewshop.com</p> <p>After review and approval, we will <strong>either</strong>:<br>- Send a <strong>free replacement</strong>, or<br>- Issue a <strong>full refund</strong></p> <p>We may request additional photos or information to verify the issue.<br>In some cases, we may request the defective item to be returned before processing the resolution.</p> <p><strong>3. Custom &amp; Made-To-Order Products</strong></p> <p>All products sold on NorthOak are <strong>custom-made or printed on demand.</strong><br>Because these products are made specifically for each order, <strong>we do not accept returns or refunds for the following reasons:</strong><br>- Incorrect size ordered<br>- Change of mind<br>- Incorrect shipping address provided by the customer<br>- Minor color differences due to screen display<br>- Custom name or personalization errors provided by the customer</p> <p>However, we understand mistakes happen. As a courtesy, we may offer <strong>a replacement with a 50% discount</strong> if you wish to reorder the correct size, color, or product.</p> <p><strong>4. Refund Processing</strong></p> <p>If your refund request is approved, refunds will be processed to your <strong>original payment method.</strong><br>Please allow <strong>5–7 business days</strong> for the refund to appear in your account depending on your bank or payment provider.<br>Once a refund has been issued, we will send a <strong>confirmation email.</strong></p> <p><strong>5. Late or Missing Refunds</strong></p> <p>If you have not received your refund:<br>- Check your bank account again.<br>- Contact your credit card company or payment provider.<br>- Contact your bank.</p> <p>Refunds can take several business days to process depending on your financial institution.<br>If 10 business days have passed since the refund confirmation and you still have not received the funds, please contact us at: contact@podcrewshop.com</p> <p><strong>6. Chargebacks &amp; Payment Disputes</strong></p> <p>If a chargeback or payment dispute is opened without contacting our support team first, we reserve the right to submit all order information, delivery confirmation, and communication records to the payment provider.<br>We are always happy to resolve any issues directly with our customers and encourage contacting us first for the fastest resolution.</p> | G15: =SUBSTITUTE(SUBSTITUTE(Templates!$B$3,"{{STORE}}",$A15),"{{EMAIL}}",$B15) -> <p><strong>Production Time</strong></p> <p>All products at NorthOak are made-to-order and produced specifically according to your selected design, size, and color. We do not keep inventory, which means each item is manufactured after your order is placed.<br>Production typically takes 5–10 business days (excluding weekends and holidays) before the order is shipped.<br>Orders enter the production process within 6 hours after being placed. Once production has started, orders cannot be modified or canceled.</p> <p><strong>Shipping Time</strong></p> <p>After production is completed, your order will be shipped according to the shipping method selected at checkout.</p> <p>Estimated delivery times:<br>Standard Shipping: 10–20 business days<br>Fast Shipping: 5–10 business days</p> <p>Delivery times may vary depending on your location, customs processing, and carrier delays.<br>Once your order has been shipped, you will receive a tracking number via email.</p> <p><strong>Estimated Delivery Time</strong></p> <p>Total estimated delivery time includes production time + shipping time.<br>Example:<br>- Standard Shipping: 15–30 business days total<br>- Fast Shipping: 10–20 business days total</p> <p>For the most accurate estimate, please check the estimated delivery date on your order confirmation email.<br>If you have any questions about your order, please contact us at: contact@podcrewshop.com</p> <p><strong>Shipping Cost</strong></p> <p>- $5.95 for orders under $90<br>- Free shipping for orders $90 and above</p> <p><strong>NorthOak is not responsible for delays caused by carriers, customs clearance, weather conditions, or peak holiday seasons.</strong></p> | H15: =SUBSTITUTE(SUBSTITUTE(SUBSTITUTE(SUBSTITUTE(SUBSTITUTE(Templates!$B$4,"{{STORE}}",$A15),"{{EMAIL}}",$B15),"{{DOMAIN}}",IF(C15<>"",C15,IFERROR(MID(B15,FIND("@",B15)+1,255),""))),"{{LAST_UPDATED}}",$E15),"{{ADDRESS_TEXT}}",IF(D15<>"",D15,"[Add mailing address]")) -> <p><strong>OVERVIEW</strong><br> Welcome to NorthOak! The terms “we”, “us” and “our” refer to NorthOak. NorthOak operates this store and website, including all related information, content, features, tools, products and services in order to provide you with a shopping experience. NorthOak is powered by Shopify. </p> <p>By visiting or using our Services, you agree to these Terms of Service.</p> <p><strong>SECTION 1 - ACCESS</strong><br> You must be at least the age of majority in your jurisdiction to use this website. </p> <p><strong>SECTION 2 - PRODUCTS</strong><br> Product colors may appear differently depending on your device display. </p> <p><strong>SECTION 3 - ORDERS</strong><br> We reserve the right to refuse or cancel orders at our discretion. </p> <p><strong>SECTION 4 - PRICES</strong><br> Prices may change without notice. </p> <p><strong>SECTION 5 - SHIPPING</strong><br> Delivery times are estimates only. </p> <p><strong>SECTION 6 - INTELLECTUAL PROPERTY</strong><br> All website content belongs to NorthOak or its licensors. </p> <p><strong>SECTION 7 - THIRD PARTY LINKS</strong><br> We are not responsible for third‑party websites linked from our store. </p> <p><strong>SECTION 8 - LIABILITY</strong><br> NorthOak is not liable for damages resulting from the use of this website. </p> <p><strong>SECTION 9 - CONTACT</strong><br> Questions about the Terms of Service should be sent to:<br> contact@podcrewshop.com </p> <hr> | I15: =SUBSTITUTE(SUBSTITUTE(SUBSTITUTE(SUBSTITUTE(SUBSTITUTE(Templates!$B$5,"{{STORE}}",$A15),"{{EMAIL}}",$B15),"{{DOMAIN}}",IF(C15<>"",C15,IFERROR(MID(B15,FIND("@",B15)+1,255),""))),"{{LAST_UPDATED}}",$E15),"{{ADDRESS_TEXT}}",IF(D15<>"",D15,"[Add mailing address]")) -> <p><strong>Last updated:</strong> March 12, 2026</p> <p> NorthOak operates this website and collects certain personal information to provide services. </p> <h2>Information We Collect</h2> <ul> <li>Name</li> <li>Email</li> <li>Shipping address</li> <li>Billing address</li> <li>Payment details</li> <li>Device information</li> </ul> <h2>How We Use Information</h2> <ul> <li>Process orders</li> <li>Provide support</li> <li>Improve the store</li> <li>Prevent fraud</li> </ul> <h2>Sharing Information</h2> <p> We may share information with Shopify, payment providers, and shipping partners to fulfill orders. </p> <h2>Cookies</h2> <p> Cookies are used to improve user experience and analyze website traffic. </p> <h2>Your Rights</h2> <p> You may request access, correction, or deletion of your personal information. </p> <h2>Security</h2> <p> We implement security measures to protect your data but cannot guarantee absolute security. </p> <h2>Contact</h2> <p> For privacy questions contact:<br> contact@podcrewshop.com </p>
A16: EverPeak | B16: contact@podcrewshop.com | E16: March 12, 2026 | F16: =SUBSTITUTE(SUBSTITUTE(Templates!$B$2,"{{STORE}}",$A16),"{{EMAIL}}",$B16) -> <h4 style="text-align: center;">Refund, Replacement &amp; Cancellation Policy</h4> <p>At EverPeak, each product is made to order and produced specifically for you after the order is placed. Because of this, we maintain a strict but fair refund and replacement policy.</p> <p><strong>1. Order Cancellation</strong></p> <p>Orders may be cancelled <strong>within 6 hours of placing the order.</strong><br>After this period, the order may already be in production and cannot be cancelled or modified.<br>To request a cancellation, please contact us immediately at: contact@podcrewshop.com</p> <p>Requests submitted after the 6-hour cancellation window cannot be guaranteed as the order may already be in production.</p> <p>If a cancellation request is approved within the allowed time window, a 30% management, processing, and transaction fee will be deducted from the total order value.<br>This fee covers costs that are non-recoverable once the order is placed, including but not limited to:<br>- Payment processing and transaction fees<br>- Order processing and administrative costs<br>- Production preparation and fulfillment system allocation<br>The remaining balance will be refunded to the original payment method.</p> <p><strong>2. Defective, Damaged, or Incorrect Items</strong></p> <p>If you receive an item that is <strong>defective, damaged during shipping, or incorrect</strong>, please contact us within <strong>72 hours after delivery confirmation.</strong><br>Your email must include:<br>- Your order number<br>- <strong>Clear photos</strong> of the product and the issue<br>- A brief description of the problem</p> <p>Please send your request to: contact@podcrewshop.com</p> <p>After review and approval, we will <strong>either</strong>:<br>- Send a <strong>free replacement</strong>, or<br>- Issue a <strong>full refund</strong></p> <p>We may request additional photos or information to verify the issue.<br>In some cases, we may request the defective item to be returned before processing the resolution.</p> <p><strong>3. Custom &amp; Made-To-Order Products</strong></p> <p>All products sold on EverPeak are <strong>custom-made or printed on demand.</strong><br>Because these products are made specifically for each order, <strong>we do not accept returns or refunds for the following reasons:</strong><br>- Incorrect size ordered<br>- Change of mind<br>- Incorrect shipping address provided by the customer<br>- Minor color differences due to screen display<br>- Custom name or personalization errors provided by the customer</p> <p>However, we understand mistakes happen. As a courtesy, we may offer <strong>a replacement with a 50% discount</strong> if you wish to reorder the correct size, color, or product.</p> <p><strong>4. Refund Processing</strong></p> <p>If your refund request is approved, refunds will be processed to your <strong>original payment method.</strong><br>Please allow <strong>5–7 business days</strong> for the refund to appear in your account depending on your bank or payment provider.<br>Once a refund has been issued, we will send a <strong>confirmation email.</strong></p> <p><strong>5. Late or Missing Refunds</strong></p> <p>If you have not received your refund:<br>- Check your bank account again.<br>- Contact your credit card company or payment provider.<br>- Contact your bank.</p> <p>Refunds can take several business days to process depending on your financial institution.<br>If 10 business days have passed since the refund confirmation and you still have not received the funds, please contact us at: contact@podcrewshop.com</p> <p><strong>6. Chargebacks &amp; Payment Disputes</strong></p> <p>If a chargeback or payment dispute is opened without contacting our support team first, we reserve the right to submit all order information, delivery confirmation, and communication records to the payment provider.<br>We are always happy to resolve any issues directly with our customers and encourage contacting us first for the fastest resolution.</p> | G16: =SUBSTITUTE(SUBSTITUTE(Templates!$B$3,"{{STORE}}",$A16),"{{EMAIL}}",$B16) -> <p><strong>Production Time</strong></p> <p>All products at EverPeak are made-to-order and produced specifically according to your selected design, size, and color. We do not keep inventory, which means each item is manufactured after your order is placed.<br>Production typically takes 5–10 business days (excluding weekends and holidays) before the order is shipped.<br>Orders enter the production process within 6 hours after being placed. Once production has started, orders cannot be modified or canceled.</p> <p><strong>Shipping Time</strong></p> <p>After production is completed, your order will be shipped according to the shipping method selected at checkout.</p> <p>Estimated delivery times:<br>Standard Shipping: 10–20 business days<br>Fast Shipping: 5–10 business days</p> <p>Delivery times may vary depending on your location, customs processing, and carrier delays.<br>Once your order has been shipped, you will receive a tracking number via email.</p> <p><strong>Estimated Delivery Time</strong></p> <p>Total estimated delivery time includes production time + shipping time.<br>Example:<br>- Standard Shipping: 15–30 business days total<br>- Fast Shipping: 10–20 business days total</p> <p>For the most accurate estimate, please check the estimated delivery date on your order confirmation email.<br>If you have any questions about your order, please contact us at: contact@podcrewshop.com</p> <p><strong>Shipping Cost</strong></p> <p>- $5.95 for orders under $90<br>- Free shipping for orders $90 and above</p> <p><strong>EverPeak is not responsible for delays caused by carriers, customs clearance, weather conditions, or peak holiday seasons.</strong></p> | H16: =SUBSTITUTE(SUBSTITUTE(SUBSTITUTE(SUBSTITUTE(SUBSTITUTE(Templates!$B$4,"{{STORE}}",$A16),"{{EMAIL}}",$B16),"{{DOMAIN}}",IF(C16<>"",C16,IFERROR(MID(B16,FIND("@",B16)+1,255),""))),"{{LAST_UPDATED}}",$E16),"{{ADDRESS_TEXT}}",IF(D16<>"",D16,"[Add mailing address]")) -> <p><strong>OVERVIEW</strong><br> Welcome to EverPeak! The terms “we”, “us” and “our” refer to EverPeak. EverPeak operates this store and website, including all related information, content, features, tools, products and services in order to provide you with a shopping experience. EverPeak is powered by Shopify. </p> <p>By visiting or using our Services, you agree to these Terms of Service.</p> <p><strong>SECTION 1 - ACCESS</strong><br> You must be at least the age of majority in your jurisdiction to use this website. </p> <p><strong>SECTION 2 - PRODUCTS</strong><br> Product colors may appear differently depending on your device display. </p> <p><strong>SECTION 3 - ORDERS</strong><br> We reserve the right to refuse or cancel orders at our discretion. </p> <p><strong>SECTION 4 - PRICES</strong><br> Prices may change without notice. </p> <p><strong>SECTION 5 - SHIPPING</strong><br> Delivery times are estimates only. </p> <p><strong>SECTION 6 - INTELLECTUAL PROPERTY</strong><br> All website content belongs to EverPeak or its licensors. </p> <p><strong>SECTION 7 - THIRD PARTY LINKS</strong><br> We are not responsible for third‑party websites linked from our store. </p> <p><strong>SECTION 8 - LIABILITY</strong><br> EverPeak is not liable for damages resulting from the use of this website. </p> <p><strong>SECTION 9 - CONTACT</strong><br> Questions about the Terms of Service should be sent to:<br> contact@podcrewshop.com </p> <hr> | I16: =SUBSTITUTE(SUBSTITUTE(SUBSTITUTE(SUBSTITUTE(SUBSTITUTE(Templates!$B$5,"{{STORE}}",$A16),"{{EMAIL}}",$B16),"{{DOMAIN}}",IF(C16<>"",C16,IFERROR(MID(B16,FIND("@",B16)+1,255),""))),"{{LAST_UPDATED}}",$E16),"{{ADDRESS_TEXT}}",IF(D16<>"",D16,"[Add mailing address]")) -> <p><strong>Last updated:</strong> March 12, 2026</p> <p> EverPeak operates this website and collects certain personal information to provide services. </p> <h2>Information We Collect</h2> <ul> <li>Name</li> <li>Email</li> <li>Shipping address</li> <li>Billing address</li> <li>Payment details</li> <li>Device information</li> </ul> <h2>How We Use Information</h2> <ul> <li>Process orders</li> <li>Provide support</li> <li>Improve the store</li> <li>Prevent fraud</li> </ul> <h2>Sharing Information</h2> <p> We may share information with Shopify, payment providers, and shipping partners to fulfill orders. </p> <h2>Cookies</h2> <p> Cookies are used to improve user experience and analyze website traffic. </p> <h2>Your Rights</h2> <p> You may request access, correction, or deletion of your personal information. </p> <h2>Security</h2> <p> We implement security measures to protect your data but cannot guarantee absolute security. </p> <h2>Contact</h2> <p> For privacy questions contact:<br> contact@podcrewshop.com </p>
A17: BoldTrail | B17: support@boldtrailshop.us | E17: March 12, 2026 | F17: =SUBSTITUTE(SUBSTITUTE(Templates!$B$2,"{{STORE}}",$A17),"{{EMAIL}}",$B17) -> <h4 style="text-align: center;">Refund, Replacement &amp; Cancellation Policy</h4> <p>At BoldTrail, each product is made to order and produced specifically for you after the order is placed. Because of this, we maintain a strict but fair refund and replacement policy.</p> <p><strong>1. Order Cancellation</strong></p> <p>Orders may be cancelled <strong>within 6 hours of placing the order.</strong><br>After this period, the order may already be in production and cannot be cancelled or modified.<br>To request a cancellation, please contact us immediately at: support@boldtrailshop.us</p> <p>Requests submitted after the 6-hour cancellation window cannot be guaranteed as the order may already be in production.</p> <p>If a cancellation request is approved within the allowed time window, a 30% management, processing, and transaction fee will be deducted from the total order value.<br>This fee covers costs that are non-recoverable once the order is placed, including but not limited to:<br>- Payment processing and transaction fees<br>- Order processing and administrative costs<br>- Production preparation and fulfillment system allocation<br>The remaining balance will be refunded to the original payment method.</p> <p><strong>2. Defective, Damaged, or Incorrect Items</strong></p> <p>If you receive an item that is <strong>defective, damaged during shipping, or incorrect</strong>, please contact us within <strong>72 hours after delivery confirmation.</strong><br>Your email must include:<br>- Your order number<br>- <strong>Clear photos</strong> of the product and the issue<br>- A brief description of the problem</p> <p>Please send your request to: support@boldtrailshop.us</p> <p>After review and approval, we will <strong>either</strong>:<br>- Send a <strong>free replacement</strong>, or<br>- Issue a <strong>full refund</strong></p> <p>We may request additional photos or information to verify the issue.<br>In some cases, we may request the defective item to be returned before processing the resolution.</p> <p><strong>3. Custom &amp; Made-To-Order Products</strong></p> <p>All products sold on BoldTrail are <strong>custom-made or printed on demand.</strong><br>Because these products are made specifically for each order, <strong>we do not accept returns or refunds for the following reasons:</strong><br>- Incorrect size ordered<br>- Change of mind<br>- Incorrect shipping address provided by the customer<br>- Minor color differences due to screen display<br>- Custom name or personalization errors provided by the customer</p> <p>However, we understand mistakes happen. As a courtesy, we may offer <strong>a replacement with a 50% discount</strong> if you wish to reorder the correct size, color, or product.</p> <p><strong>4. Refund Processing</strong></p> <p>If your refund request is approved, refunds will be processed to your <strong>original payment method.</strong><br>Please allow <strong>5–7 business days</strong> for the refund to appear in your account depending on your bank or payment provider.<br>Once a refund has been issued, we will send a <strong>confirmation email.</strong></p> <p><strong>5. Late or Missing Refunds</strong></p> <p>If you have not received your refund:<br>- Check your bank account again.<br>- Contact your credit card company or payment provider.<br>- Contact your bank.</p> <p>Refunds can take several business days to process depending on your financial institution.<br>If 10 business days have passed since the refund confirmation and you still have not received the funds, please contact us at: support@boldtrailshop.us</p> <p><strong>6. Chargebacks &amp; Payment Disputes</strong></p> <p>If a chargeback or payment dispute is opened without contacting our support team first, we reserve the right to submit all order information, delivery confirmation, and communication records to the payment provider.<br>We are always happy to resolve any issues directly with our customers and encourage contacting us first for the fastest resolution.</p> | G17: =SUBSTITUTE(SUBSTITUTE(Templates!$B$3,"{{STORE}}",$A17),"{{EMAIL}}",$B17) -> <p><strong>Production Time</strong></p> <p>All products at BoldTrail are made-to-order and produced specifically according to your selected design, size, and color. We do not keep inventory, which means each item is manufactured after your order is placed.<br>Production typically takes 5–10 business days (excluding weekends and holidays) before the order is shipped.<br>Orders enter the production process within 6 hours after being placed. Once production has started, orders cannot be modified or canceled.</p> <p><strong>Shipping Time</strong></p> <p>After production is completed, your order will be shipped according to the shipping method selected at checkout.</p> <p>Estimated delivery times:<br>Standard Shipping: 10–20 business days<br>Fast Shipping: 5–10 business days</p> <p>Delivery times may vary depending on your location, customs processing, and carrier delays.<br>Once your order has been shipped, you will receive a tracking number via email.</p> <p><strong>Estimated Delivery Time</strong></p> <p>Total estimated delivery time includes production time + shipping time.<br>Example:<br>- Standard Shipping: 15–30 business days total<br>- Fast Shipping: 10–20 business days total</p> <p>For the most accurate estimate, please check the estimated delivery date on your order confirmation email.<br>If you have any questions about your order, please contact us at: support@boldtrailshop.us</p> <p><strong>Shipping Cost</strong></p> <p>- $5.95 for orders under $90<br>- Free shipping for orders $90 and above</p> <p><strong>BoldTrail is not responsible for delays caused by carriers, customs clearance, weather conditions, or peak holiday seasons.</strong></p> | H17: =SUBSTITUTE(SUBSTITUTE(SUBSTITUTE(SUBSTITUTE(SUBSTITUTE(Templates!$B$4,"{{STORE}}",$A17),"{{EMAIL}}",$B17),"{{DOMAIN}}",IF(C17<>"",C17,IFERROR(MID(B17,FIND("@",B17)+1,255),""))),"{{LAST_UPDATED}}",$E17),"{{ADDRESS_TEXT}}",IF(D17<>"",D17,"[Add mailing address]")) -> <p><strong>OVERVIEW</strong><br> Welcome to BoldTrail! The terms “we”, “us” and “our” refer to BoldTrail. BoldTrail operates this store and website, including all related information, content, features, tools, products and services in order to provide you with a shopping experience. BoldTrail is powered by Shopify. </p> <p>By visiting or using our Services, you agree to these Terms of Service.</p> <p><strong>SECTION 1 - ACCESS</strong><br> You must be at least the age of majority in your jurisdiction to use this website. </p> <p><strong>SECTION 2 - PRODUCTS</strong><br> Product colors may appear differently depending on your device display. </p> <p><strong>SECTION 3 - ORDERS</strong><br> We reserve the right to refuse or cancel orders at our discretion. </p> <p><strong>SECTION 4 - PRICES</strong><br> Prices may change without notice. </p> <p><strong>SECTION 5 - SHIPPING</strong><br> Delivery times are estimates only. </p> <p><strong>SECTION 6 - INTELLECTUAL PROPERTY</strong><br> All website content belongs to BoldTrail or its licensors. </p> <p><strong>SECTION 7 - THIRD PARTY LINKS</strong><br> We are not responsible for third‑party websites linked from our store. </p> <p><strong>SECTION 8 - LIABILITY</strong><br> BoldTrail is not liable for damages resulting from the use of this website. </p> <p><strong>SECTION 9 - CONTACT</strong><br> Questions about the Terms of Service should be sent to:<br> support@boldtrailshop.us </p> <hr> | I17: =SUBSTITUTE(SUBSTITUTE(SUBSTITUTE(SUBSTITUTE(SUBSTITUTE(Templates!$B$5,"{{STORE}}",$A17),"{{EMAIL}}",$B17),"{{DOMAIN}}",IF(C17<>"",C17,IFERROR(MID(B17,FIND("@",B17)+1,255),""))),"{{LAST_UPDATED}}",$E17),"{{ADDRESS_TEXT}}",IF(D17<>"",D17,"[Add mailing address]")) -> <p><strong>Last updated:</strong> March 12, 2026</p> <p> BoldTrail operates this website and collects certain personal information to provide services. </p> <h2>Information We Collect</h2> <ul> <li>Name</li> <li>Email</li> <li>Shipping address</li> <li>Billing address</li> <li>Payment details</li> <li>Device information</li> </ul> <h2>How We Use Information</h2> <ul> <li>Process orders</li> <li>Provide support</li> <li>Improve the store</li> <li>Prevent fraud</li> </ul> <h2>Sharing Information</h2> <p> We may share information with Shopify, payment providers, and shipping partners to fulfill orders. </p> <h2>Cookies</h2> <p> Cookies are used to improve user experience and analyze website traffic. </p> <h2>Your Rights</h2> <p> You may request access, correction, or deletion of your personal information. </p> <h2>Security</h2> <p> We implement security measures to protect your data but cannot guarantee absolute security. </p> <h2>Contact</h2> <p> For privacy questions contact:<br> support@boldtrailshop.us </p>
A18: TrueNorth | B18: contact@podcrewshop.com | E18: March 12, 2026 | F18: =SUBSTITUTE(SUBSTITUTE(Templates!$B$2,"{{STORE}}",$A18),"{{EMAIL}}",$B18) -> <h4 style="text-align: center;">Refund, Replacement &amp; Cancellation Policy</h4> <p>At TrueNorth, each product is made to order and produced specifically for you after the order is placed. Because of this, we maintain a strict but fair refund and replacement policy.</p> <p><strong>1. Order Cancellation</strong></p> <p>Orders may be cancelled <strong>within 6 hours of placing the order.</strong><br>After this period, the order may already be in production and cannot be cancelled or modified.<br>To request a cancellation, please contact us immediately at: contact@podcrewshop.com</p> <p>Requests submitted after the 6-hour cancellation window cannot be guaranteed as the order may already be in production.</p> <p>If a cancellation request is approved within the allowed time window, a 30% management, processing, and transaction fee will be deducted from the total order value.<br>This fee covers costs that are non-recoverable once the order is placed, including but not limited to:<br>- Payment processing and transaction fees<br>- Order processing and administrative costs<br>- Production preparation and fulfillment system allocation<br>The remaining balance will be refunded to the original payment method.</p> <p><strong>2. Defective, Damaged, or Incorrect Items</strong></p> <p>If you receive an item that is <strong>defective, damaged during shipping, or incorrect</strong>, please contact us within <strong>72 hours after delivery confirmation.</strong><br>Your email must include:<br>- Your order number<br>- <strong>Clear photos</strong> of the product and the issue<br>- A brief description of the problem</p> <p>Please send your request to: contact@podcrewshop.com</p> <p>After review and approval, we will <strong>either</strong>:<br>- Send a <strong>free replacement</strong>, or<br>- Issue a <strong>full refund</strong></p> <p>We may request additional photos or information to verify the issue.<br>In some cases, we may request the defective item to be returned before processing the resolution.</p> <p><strong>3. Custom &amp; Made-To-Order Products</strong></p> <p>All products sold on TrueNorth are <strong>custom-made or printed on demand.</strong><br>Because these products are made specifically for each order, <strong>we do not accept returns or refunds for the following reasons:</strong><br>- Incorrect size ordered<br>- Change of mind<br>- Incorrect shipping address provided by the customer<br>- Minor color differences due to screen display<br>- Custom name or personalization errors provided by the customer</p> <p>However, we understand mistakes happen. As a courtesy, we may offer <strong>a replacement with a 50% discount</strong> if you wish to reorder the correct size, color, or product.</p> <p><strong>4. Refund Processing</strong></p> <p>If your refund request is approved, refunds will be processed to your <strong>original payment method.</strong><br>Please allow <strong>5–7 business days</strong> for the refund to appear in your account depending on your bank or payment provider.<br>Once a refund has been issued, we will send a <strong>confirmation email.</strong></p> <p><strong>5. Late or Missing Refunds</strong></p> <p>If you have not received your refund:<br>- Check your bank account again.<br>- Contact your credit card company or payment provider.<br>- Contact your bank.</p> <p>Refunds can take several business days to process depending on your financial institution.<br>If 10 business days have passed since the refund confirmation and you still have not received the funds, please contact us at: contact@podcrewshop.com</p> <p><strong>6. Chargebacks &amp; Payment Disputes</strong></p> <p>If a chargeback or payment dispute is opened without contacting our support team first, we reserve the right to submit all order information, delivery confirmation, and communication records to the payment provider.<br>We are always happy to resolve any issues directly with our customers and encourage contacting us first for the fastest resolution.</p> | G18: =SUBSTITUTE(SUBSTITUTE(Templates!$B$3,"{{STORE}}",$A18),"{{EMAIL}}",$B18) -> <p><strong>Production Time</strong></p> <p>All products at TrueNorth are made-to-order and produced specifically according to your selected design, size, and color. We do not keep inventory, which means each item is manufactured after your order is placed.<br>Production typically takes 5–10 business days (excluding weekends and holidays) before the order is shipped.<br>Orders enter the production process within 6 hours after being placed. Once production has started, orders cannot be modified or canceled.</p> <p><strong>Shipping Time</strong></p> <p>After production is completed, your order will be shipped according to the shipping method selected at checkout.</p> <p>Estimated delivery times:<br>Standard Shipping: 10–20 business days<br>Fast Shipping: 5–10 business days</p> <p>Delivery times may vary depending on your location, customs processing, and carrier delays.<br>Once your order has been shipped, you will receive a tracking number via email.</p> <p><strong>Estimated Delivery Time</strong></p> <p>Total estimated delivery time includes production time + shipping time.<br>Example:<br>- Standard Shipping: 15–30 business days total<br>- Fast Shipping: 10–20 business days total</p> <p>For the most accurate estimate, please check the estimated delivery date on your order confirmation email.<br>If you have any questions about your order, please contact us at: contact@podcrewshop.com</p> <p><strong>Shipping Cost</strong></p> <p>- $5.95 for orders under $90<br>- Free shipping for orders $90 and above</p> <p><strong>TrueNorth is not responsible for delays caused by carriers, customs clearance, weather conditions, or peak holiday seasons.</strong></p> | H18: =SUBSTITUTE(SUBSTITUTE(SUBSTITUTE(SUBSTITUTE(SUBSTITUTE(Templates!$B$4,"{{STORE}}",$A18),"{{EMAIL}}",$B18),"{{DOMAIN}}",IF(C18<>"",C18,IFERROR(MID(B18,FIND("@",B18)+1,255),""))),"{{LAST_UPDATED}}",$E18),"{{ADDRESS_TEXT}}",IF(D18<>"",D18,"[Add mailing address]")) -> <p><strong>OVERVIEW</strong><br> Welcome to TrueNorth! The terms “we”, “us” and “our” refer to TrueNorth. TrueNorth operates this store and website, including all related information, content, features, tools, products and services in order to provide you with a shopping experience. TrueNorth is powered by Shopify. </p> <p>By visiting or using our Services, you agree to these Terms of Service.</p> <p><strong>SECTION 1 - ACCESS</strong><br> You must be at least the age of majority in your jurisdiction to use this website. </p> <p><strong>SECTION 2 - PRODUCTS</strong><br> Product colors may appear differently depending on your device display. </p> <p><strong>SECTION 3 - ORDERS</strong><br> We reserve the right to refuse or cancel orders at our discretion. </p> <p><strong>SECTION 4 - PRICES</strong><br> Prices may change without notice. </p> <p><strong>SECTION 5 - SHIPPING</strong><br> Delivery times are estimates only. </p> <p><strong>SECTION 6 - INTELLECTUAL PROPERTY</strong><br> All website content belongs to TrueNorth or its licensors. </p> <p><strong>SECTION 7 - THIRD PARTY LINKS</strong><br> We are not responsible for third‑party websites linked from our store. </p> <p><strong>SECTION 8 - LIABILITY</strong><br> TrueNorth is not liable for damages resulting from the use of this website. </p> <p><strong>SECTION 9 - CONTACT</strong><br> Questions about the Terms of Service should be sent to:<br> contact@podcrewshop.com </p> <hr> | I18: =SUBSTITUTE(SUBSTITUTE(SUBSTITUTE(SUBSTITUTE(SUBSTITUTE(Templates!$B$5,"{{STORE}}",$A18),"{{EMAIL}}",$B18),"{{DOMAIN}}",IF(C18<>"",C18,IFERROR(MID(B18,FIND("@",B18)+1,255),""))),"{{LAST_UPDATED}}",$E18),"{{ADDRESS_TEXT}}",IF(D18<>"",D18,"[Add mailing address]")) -> <p><strong>Last updated:</strong> March 12, 2026</p> <p> TrueNorth operates this website and collects certain personal information to provide services. </p> <h2>Information We Collect</h2> <ul> <li>Name</li> <li>Email</li> <li>Shipping address</li> <li>Billing address</li> <li>Payment details</li> <li>Device information</li> </ul> <h2>How We Use Information</h2> <ul> <li>Process orders</li> <li>Provide support</li> <li>Improve the store</li> <li>Prevent fraud</li> </ul> <h2>Sharing Information</h2> <p> We may share information with Shopify, payment providers, and shipping partners to fulfill orders. </p> <h2>Cookies</h2> <p> Cookies are used to improve user experience and analyze website traffic. </p> <h2>Your Rights</h2> <p> You may request access, correction, or deletion of your personal information. </p> <h2>Security</h2> <p> We implement security measures to protect your data but cannot guarantee absolute security. </p> <h2>Contact</h2> <p> For privacy questions contact:<br> contact@podcrewshop.com </p>
... A45: Themediaagencygroup | B45: contact@podcrewshop.com | E45: March 12, 2039 | F45: =SUBSTITUTE(SUBSTITUTE(Templates!$B$2,"{{STORE}}",$A45),"{{EMAIL}}",$B45) -> <h4 style="text-align: center;">Refund, Replacement &amp; Cancellation Policy</h4> <p>At Themediaagencygroup, each product is made to order and produced specifically for you after the order is placed. Because of this, we maintain a strict but fair refund and replacement policy.</p> <p><strong>1. Order Cancellation</strong></p> <p>Orders may be cancelled <strong>within 6 hours of placing the order.</strong><br>After this period, the order may already be in production and cannot be cancelled or modified.<br>To request a cancellation, please contact us immediately at: contact@podcrewshop.com</p> <p>Requests submitted after the 6-hour cancellation window cannot be guaranteed as the order may already be in production.</p> <p>If a cancellation request is approved within the allowed time window, a 30% management, processing, and transaction fee will be deducted from the total order value.<br>This fee covers costs that are non-recoverable once the order is placed, including but not limited to:<br>- Payment processing and transaction fees<br>- Order processing and administrative costs<br>- Production preparation and fulfillment system allocation<br>The remaining balance will be refunded to the original payment method.</p> <p><strong>2. Defective, Damaged, or Incorrect Items</strong></p> <p>If you receive an item that is <strong>defective, damaged during shipping, or incorrect</strong>, please contact us within <strong>72 hours after delivery confirmation.</strong><br>Your email must include:<br>- Your order number<br>- <strong>Clear photos</strong> of the product and the issue<br>- A brief description of the problem</p> <p>Please send your request to: contact@podcrewshop.com</p> <p>After review and approval, we will <strong>either</strong>:<br>- Send a <strong>free replacement</strong>, or<br>- Issue a <strong>full refund</strong></p> <p>We may request additional photos or information to verify the issue.<br>In some cases, we may request the defective item to be returned before processing the resolution.</p> <p><strong>3. Custom &amp; Made-To-Order Products</strong></p> <p>All products sold on Themediaagencygroup are <strong>custom-made or printed on demand.</strong><br>Because these products are made specifically for each order, <strong>we do not accept returns or refunds for the following reasons:</strong><br>- Incorrect size ordered<br>- Change of mind<br>- Incorrect shipping address provided by the customer<br>- Minor color differences due to screen display<br>- Custom name or personalization errors provided by the customer</p> <p>However, we understand mistakes happen. As a courtesy, we may offer <strong>a replacement with a 50% discount</strong> if you wish to reorder the correct size, color, or product.</p> <p><strong>4. Refund Processing</strong></p> <p>If your refund request is approved, refunds will be processed to your <strong>original payment method.</strong><br>Please allow <strong>5–7 business days</strong> for the refund to appear in your account depending on your bank or payment provider.<br>Once a refund has been issued, we will send a <strong>confirmation email.</strong></p> <p><strong>5. Late or Missing Refunds</strong></p> <p>If you have not received your refund:<br>- Check your bank account again.<br>- Contact your credit card company or payment provider.<br>- Contact your bank.</p> <p>Refunds can take several business days to process depending on your financial institution.<br>If 10 business days have passed since the refund confirmation and you still have not received the funds, please contact us at: contact@podcrewshop.com</p> <p><strong>6. Chargebacks &amp; Payment Disputes</strong></p> <p>If a chargeback or payment dispute is opened without contacting our support team first, we reserve the right to submit all order information, delivery confirmation, and communication records to the payment provider.<br>We are always happy to resolve any issues directly with our customers and encourage contacting us first for the fastest resolution.</p> | G45: =SUBSTITUTE(SUBSTITUTE(Templates!$B$3,"{{STORE}}",$A45),"{{EMAIL}}",$B45) -> <p><strong>Production Time</strong></p> <p>All products at Themediaagencygroup are made-to-order and produced specifically according to your selected design, size, and color. We do not keep inventory, which means each item is manufactured after your order is placed.<br>Production typically takes 5–10 business days (excluding weekends and holidays) before the order is shipped.<br>Orders enter the production process within 6 hours after being placed. Once production has started, orders cannot be modified or canceled.</p> <p><strong>Shipping Time</strong></p> <p>After production is completed, your order will be shipped according to the shipping method selected at checkout.</p> <p>Estimated delivery times:<br>Standard Shipping: 10–20 business days<br>Fast Shipping: 5–10 business days</p> <p>Delivery times may vary depending on your location, customs processing, and carrier delays.<br>Once your order has been shipped, you will receive a tracking number via email.</p> <p><strong>Estimated Delivery Time</strong></p> <p>Total estimated delivery time includes production time + shipping time.<br>Example:<br>- Standard Shipping: 15–30 business days total<br>- Fast Shipping: 10–20 business days total</p> <p>For the most accurate estimate, please check the estimated delivery date on your order confirmation email.<br>If you have any questions about your order, please contact us at: contact@podcrewshop.com</p> <p><strong>Shipping Cost</strong></p> <p>- $5.95 for orders under $90<br>- Free shipping for orders $90 and above</p> <p><strong>Themediaagencygroup is not responsible for delays caused by carriers, customs clearance, weather conditions, or peak holiday seasons.</strong></p> | H45: =SUBSTITUTE(SUBSTITUTE(SUBSTITUTE(SUBSTITUTE(SUBSTITUTE(Templates!$B$4,"{{STORE}}",$A45),"{{EMAIL}}",$B45),"{{DOMAIN}}",IF(C45<>"",C45,IFERROR(MID(B45,FIND("@",B45)+1,255),""))),"{{LAST_UPDATED}}",$E45),"{{ADDRESS_TEXT}}",IF(D45<>"",D45,"[Add mailing address]")) -> <p><strong>OVERVIEW</strong><br> Welcome to Themediaagencygroup! The terms “we”, “us” and “our” refer to Themediaagencygroup. Themediaagencygroup operates this store and website, including all related information, content, features, tools, products and services in order to provide you with a shopping experience. Themediaagencygroup is powered by Shopify. </p> <p>By visiting or using our Services, you agree to these Terms of Service.</p> <p><strong>SECTION 1 - ACCESS</strong><br> You must be at least the age of majority in your jurisdiction to use this website. </p> <p><strong>SECTION 2 - PRODUCTS</strong><br> Product colors may appear differently depending on your device display. </p> <p><strong>SECTION 3 - ORDERS</strong><br> We reserve the right to refuse or cancel orders at our discretion. </p> <p><strong>SECTION 4 - PRICES</strong><br> Prices may change without notice. </p> <p><strong>SECTION 5 - SHIPPING</strong><br> Delivery times are estimates only. </p> <p><strong>SECTION 6 - INTELLECTUAL PROPERTY</strong><br> All website content belongs to Themediaagencygroup or its licensors. </p> <p><strong>SECTION 7 - THIRD PARTY LINKS</strong><br> We are not responsible for third‑party websites linked from our store. </p> <p><strong>SECTION 8 - LIABILITY</strong><br> Themediaagencygroup is not liable for damages resulting from the use of this website. </p> <p><strong>SECTION 9 - CONTACT</strong><br> Questions about the Terms of Service should be sent to:<br> contact@podcrewshop.com </p> <hr> | I45: =SUBSTITUTE(SUBSTITUTE(SUBSTITUTE(SUBSTITUTE(SUBSTITUTE(Templates!$B$5,"{{STORE}}",$A45),"{{EMAIL}}",$B45),"{{DOMAIN}}",IF(C45<>"",C45,IFERROR(MID(B45,FIND("@",B45)+1,255),""))),"{{LAST_UPDATED}}",$E45),"{{ADDRESS_TEXT}}",IF(D45<>"",D45,"[Add mailing address]")) -> <p><strong>Last updated:</strong> March 12, 2039</p> <p> Themediaagencygroup operates this website and collects certain personal information to provide services. </p> <h2>Information We Collect</h2> <ul> <li>Name</li> <li>Email</li> <li>Shipping address</li> <li>Billing address</li> <li>Payment details</li> <li>Device information</li> </ul> <h2>How We Use Information</h2> <ul> <li>Process orders</li> <li>Provide support</li> <li>Improve the store</li> <li>Prevent fraud</li> </ul> <h2>Sharing Information</h2> <p> We may share information with Shopify, payment providers, and shipping partners to fulfill orders. </p> <h2>Cookies</h2> <p> Cookies are used to improve user experience and analyze website traffic. </p> <h2>Your Rights</h2> <p> You may request access, correction, or deletion of your personal information. </p> <h2>Security</h2> <p> We implement security measures to protect your data but cannot guarantee absolute security. </p> <h2>Contact</h2> <p> For privacy questions contact:<br> contact@podcrewshop.com </p>
E46: March 12, 2040 | F46: =SUBSTITUTE(SUBSTITUTE(Templates!$B$2,"{{STORE}}",$A46),"{{EMAIL}}",$B46) -> <h4 style="text-align: center;">Refund, Replacement &amp; Cancellation Policy</h4> <p>At , each product is made to order and produced specifically for you after the order is placed. Because of this, we maintain a strict but fair refund and replacement policy.</p> <p><strong>1. Order Cancellation</strong></p> <p>Orders may be cancelled <strong>within 6 hours of placing the order.</strong><br>After this period, the order may already be in production and cannot be cancelled or modified.<br>To request a cancellation, please contact us immediately at: </p> <p>Requests submitted after the 6-hour cancellation window cannot be guaranteed as the order may already be in production.</p> <p>If a cancellation request is approved within the allowed time window, a 30% management, processing, and transaction fee will be deducted from the total order value.<br>This fee covers costs that are non-recoverable once the order is placed, including but not limited to:<br>- Payment processing and transaction fees<br>- Order processing and administrative costs<br>- Production preparation and fulfillment system allocation<br>The remaining balance will be refunded to the original payment method.</p> <p><strong>2. Defective, Damaged, or Incorrect Items</strong></p> <p>If you receive an item that is <strong>defective, damaged during shipping, or incorrect</strong>, please contact us within <strong>72 hours after delivery confirmation.</strong><br>Your email must include:<br>- Your order number<br>- <strong>Clear photos</strong> of the product and the issue<br>- A brief description of the problem</p> <p>Please send your request to: </p> <p>After review and approval, we will <strong>either</strong>:<br>- Send a <strong>free replacement</strong>, or<br>- Issue a <strong>full refund</strong></p> <p>We may request additional photos or information to verify the issue.<br>In some cases, we may request the defective item to be returned before processing the resolution.</p> <p><strong>3. Custom &amp; Made-To-Order Products</strong></p> <p>All products sold on are <strong>custom-made or printed on demand.</strong><br>Because these products are made specifically for each order, <strong>we do not accept returns or refunds for the following reasons:</strong><br>- Incorrect size ordered<br>- Change of mind<br>- Incorrect shipping address provided by the customer<br>- Minor color differences due to screen display<br>- Custom name or personalization errors provided by the customer</p> <p>However, we understand mistakes happen. As a courtesy, we may offer <strong>a replacement with a 50% discount</strong> if you wish to reorder the correct size, color, or product.</p> <p><strong>4. Refund Processing</strong></p> <p>If your refund request is approved, refunds will be processed to your <strong>original payment method.</strong><br>Please allow <strong>5–7 business days</strong> for the refund to appear in your account depending on your bank or payment provider.<br>Once a refund has been issued, we will send a <strong>confirmation email.</strong></p> <p><strong>5. Late or Missing Refunds</strong></p> <p>If you have not received your refund:<br>- Check your bank account again.<br>- Contact your credit card company or payment provider.<br>- Contact your bank.</p> <p>Refunds can take several business days to process depending on your financial institution.<br>If 10 business days have passed since the refund confirmation and you still have not received the funds, please contact us at: </p> <p><strong>6. Chargebacks &amp; Payment Disputes</strong></p> <p>If a chargeback or payment dispute is opened without contacting our support team first, we reserve the right to submit all order information, delivery confirmation, and communication records to the payment provider.<br>We are always happy to resolve any issues directly with our customers and encourage contacting us first for the fastest resolution.</p> | G46: =SUBSTITUTE(SUBSTITUTE(Templates!$B$3,"{{STORE}}",$A46),"{{EMAIL}}",$B46) -> <p><strong>Production Time</strong></p> <p>All products at are made-to-order and produced specifically according to your selected design, size, and color. We do not keep inventory, which means each item is manufactured after your order is placed.<br>Production typically takes 5–10 business days (excluding weekends and holidays) before the order is shipped.<br>Orders enter the production process within 6 hours after being placed. Once production has started, orders cannot be modified or canceled.</p> <p><strong>Shipping Time</strong></p> <p>After production is completed, your order will be shipped according to the shipping method selected at checkout.</p> <p>Estimated delivery times:<br>Standard Shipping: 10–20 business days<br>Fast Shipping: 5–10 business days</p> <p>Delivery times may vary depending on your location, customs processing, and carrier delays.<br>Once your order has been shipped, you will receive a tracking number via email.</p> <p><strong>Estimated Delivery Time</strong></p> <p>Total estimated delivery time includes production time + shipping time.<br>Example:<br>- Standard Shipping: 15–30 business days total<br>- Fast Shipping: 10–20 business days total</p> <p>For the most accurate estimate, please check the estimated delivery date on your order confirmation email.<br>If you have any questions about your order, please contact us at: </p> <p><strong>Shipping Cost</strong></p> <p>- $5.95 for orders under $90<br>- Free shipping for orders $90 and above</p> <p><strong> is not responsible for delays caused by carriers, customs clearance, weather conditions, or peak holiday seasons.</strong></p> | H46: =SUBSTITUTE(SUBSTITUTE(SUBSTITUTE(SUBSTITUTE(SUBSTITUTE(Templates!$B$4,"{{STORE}}",$A46),"{{EMAIL}}",$B46),"{{DOMAIN}}",IF(C46<>"",C46,IFERROR(MID(B46,FIND("@",B46)+1,255),""))),"{{LAST_UPDATED}}",$E46),"{{ADDRESS_TEXT}}",IF(D46<>"",D46,"[Add mailing address]")) -> <p><strong>OVERVIEW</strong><br> Welcome to ! The terms “we”, “us” and “our” refer to . operates this store and website, including all related information, content, features, tools, products and services in order to provide you with a shopping experience. is powered by Shopify. </p> <p>By visiting or using our Services, you agree to these Terms of Service.</p> <p><strong>SECTION 1 - ACCESS</strong><br> You must be at least the age of majority in your jurisdiction to use this website. </p> <p><strong>SECTION 2 - PRODUCTS</strong><br> Product colors may appear differently depending on your device display. </p> <p><strong>SECTION 3 - ORDERS</strong><br> We reserve the right to refuse or cancel orders at our discretion. </p> <p><strong>SECTION 4 - PRICES</strong><br> Prices may change without notice. </p> <p><strong>SECTION 5 - SHIPPING</strong><br> Delivery times are estimates only. </p> <p><strong>SECTION 6 - INTELLECTUAL PROPERTY</strong><br> All website content belongs to or its licensors. </p> <p><strong>SECTION 7 - THIRD PARTY LINKS</strong><br> We are not responsible for third‑party websites linked from our store. </p> <p><strong>SECTION 8 - LIABILITY</strong><br> is not liable for damages resulting from the use of this website. </p> <p><strong>SECTION 9 - CONTACT</strong><br> Questions about the Terms of Service should be sent to:<br> </p> <hr> | I46: =SUBSTITUTE(SUBSTITUTE(SUBSTITUTE(SUBSTITUTE(SUBSTITUTE(Templates!$B$5,"{{STORE}}",$A46),"{{EMAIL}}",$B46),"{{DOMAIN}}",IF(C46<>"",C46,IFERROR(MID(B46,FIND("@",B46)+1,255),""))),"{{LAST_UPDATED}}",$E46),"{{ADDRESS_TEXT}}",IF(D46<>"",D46,"[Add mailing address]")) -> <p><strong>Last updated:</strong> March 12, 2040</p> <p> operates this website and collects certain personal information to provide services. </p> <h2>Information We Collect</h2> <ul> <li>Name</li> <li>Email</li> <li>Shipping address</li> <li>Billing address</li> <li>Payment details</li> <li>Device information</li> </ul> <h2>How We Use Information</h2> <ul> <li>Process orders</li> <li>Provide support</li> <li>Improve the store</li> <li>Prevent fraud</li> </ul> <h2>Sharing Information</h2> <p> We may share information with Shopify, payment providers, and shipping partners to fulfill orders. </p> <h2>Cookies</h2> <p> Cookies are used to improve user experience and analyze website traffic. </p> <h2>Your Rights</h2> <p> You may request access, correction, or deletion of your personal information. </p> <h2>Security</h2> <p> We implement security measures to protect your data but cannot guarantee absolute security. </p> <h2>Contact</h2> <p> For privacy questions contact:<br> </p>
E47: March 12, 2041 | F47: =SUBSTITUTE(SUBSTITUTE(Templates!$B$2,"{{STORE}}",$A47),"{{EMAIL}}",$B47) -> <h4 style="text-align: center;">Refund, Replacement &amp; Cancellation Policy</h4> <p>At , each product is made to order and produced specifically for you after the order is placed. Because of this, we maintain a strict but fair refund and replacement policy.</p> <p><strong>1. Order Cancellation</strong></p> <p>Orders may be cancelled <strong>within 6 hours of placing the order.</strong><br>After this period, the order may already be in production and cannot be cancelled or modified.<br>To request a cancellation, please contact us immediately at: </p> <p>Requests submitted after the 6-hour cancellation window cannot be guaranteed as the order may already be in production.</p> <p>If a cancellation request is approved within the allowed time window, a 30% management, processing, and transaction fee will be deducted from the total order value.<br>This fee covers costs that are non-recoverable once the order is placed, including but not limited to:<br>- Payment processing and transaction fees<br>- Order processing and administrative costs<br>- Production preparation and fulfillment system allocation<br>The remaining balance will be refunded to the original payment method.</p> <p><strong>2. Defective, Damaged, or Incorrect Items</strong></p> <p>If you receive an item that is <strong>defective, damaged during shipping, or incorrect</strong>, please contact us within <strong>72 hours after delivery confirmation.</strong><br>Your email must include:<br>- Your order number<br>- <strong>Clear photos</strong> of the product and the issue<br>- A brief description of the problem</p> <p>Please send your request to: </p> <p>After review and approval, we will <strong>either</strong>:<br>- Send a <strong>free replacement</strong>, or<br>- Issue a <strong>full refund</strong></p> <p>We may request additional photos or information to verify the issue.<br>In some cases, we may request the defective item to be returned before processing the resolution.</p> <p><strong>3. Custom &amp; Made-To-Order Products</strong></p> <p>All products sold on are <strong>custom-made or printed on demand.</strong><br>Because these products are made specifically for each order, <strong>we do not accept returns or refunds for the following reasons:</strong><br>- Incorrect size ordered<br>- Change of mind<br>- Incorrect shipping address provided by the customer<br>- Minor color differences due to screen display<br>- Custom name or personalization errors provided by the customer</p> <p>However, we understand mistakes happen. As a courtesy, we may offer <strong>a replacement with a 50% discount</strong> if you wish to reorder the correct size, color, or product.</p> <p><strong>4. Refund Processing</strong></p> <p>If your refund request is approved, refunds will be processed to your <strong>original payment method.</strong><br>Please allow <strong>5–7 business days</strong> for the refund to appear in your account depending on your bank or payment provider.<br>Once a refund has been issued, we will send a <strong>confirmation email.</strong></p> <p><strong>5. Late or Missing Refunds</strong></p> <p>If you have not received your refund:<br>- Check your bank account again.<br>- Contact your credit card company or payment provider.<br>- Contact your bank.</p> <p>Refunds can take several business days to process depending on your financial institution.<br>If 10 business days have passed since the refund confirmation and you still have not received the funds, please contact us at: </p> <p><strong>6. Chargebacks &amp; Payment Disputes</strong></p> <p>If a chargeback or payment dispute is opened without contacting our support team first, we reserve the right to submit all order information, delivery confirmation, and communication records to the payment provider.<br>We are always happy to resolve any issues directly with our customers and encourage contacting us first for the fastest resolution.</p> | G47: =SUBSTITUTE(SUBSTITUTE(Templates!$B$3,"{{STORE}}",$A47),"{{EMAIL}}",$B47) -> <p><strong>Production Time</strong></p> <p>All products at are made-to-order and produced specifically according to your selected design, size, and color. We do not keep inventory, which means each item is manufactured after your order is placed.<br>Production typically takes 5–10 business days (excluding weekends and holidays) before the order is shipped.<br>Orders enter the production process within 6 hours after being placed. Once production has started, orders cannot be modified or canceled.</p> <p><strong>Shipping Time</strong></p> <p>After production is completed, your order will be shipped according to the shipping method selected at checkout.</p> <p>Estimated delivery times:<br>Standard Shipping: 10–20 business days<br>Fast Shipping: 5–10 business days</p> <p>Delivery times may vary depending on your location, customs processing, and carrier delays.<br>Once your order has been shipped, you will receive a tracking number via email.</p> <p><strong>Estimated Delivery Time</strong></p> <p>Total estimated delivery time includes production time + shipping time.<br>Example:<br>- Standard Shipping: 15–30 business days total<br>- Fast Shipping: 10–20 business days total</p> <p>For the most accurate estimate, please check the estimated delivery date on your order confirmation email.<br>If you have any questions about your order, please contact us at: </p> <p><strong>Shipping Cost</strong></p> <p>- $5.95 for orders under $90<br>- Free shipping for orders $90 and above</p> <p><strong> is not responsible for delays caused by carriers, customs clearance, weather conditions, or peak holiday seasons.</strong></p> | H47: =SUBSTITUTE(SUBSTITUTE(SUBSTITUTE(SUBSTITUTE(SUBSTITUTE(Templates!$B$4,"{{STORE}}",$A47),"{{EMAIL}}",$B47),"{{DOMAIN}}",IF(C47<>"",C47,IFERROR(MID(B47,FIND("@",B47)+1,255),""))),"{{LAST_UPDATED}}",$E47),"{{ADDRESS_TEXT}}",IF(D47<>"",D47,"[Add mailing address]")) -> <p><strong>OVERVIEW</strong><br> Welcome to ! The terms “we”, “us” and “our” refer to . operates this store and website, including all related information, content, features, tools, products and services in order to provide you with a shopping experience. is powered by Shopify. </p> <p>By visiting or using our Services, you agree to these Terms of Service.</p> <p><strong>SECTION 1 - ACCESS</strong><br> You must be at least the age of majority in your jurisdiction to use this website. </p> <p><strong>SECTION 2 - PRODUCTS</strong><br> Product colors may appear differently depending on your device display. </p> <p><strong>SECTION 3 - ORDERS</strong><br> We reserve the right to refuse or cancel orders at our discretion. </p> <p><strong>SECTION 4 - PRICES</strong><br> Prices may change without notice. </p> <p><strong>SECTION 5 - SHIPPING</strong><br> Delivery times are estimates only. </p> <p><strong>SECTION 6 - INTELLECTUAL PROPERTY</strong><br> All website content belongs to or its licensors. </p> <p><strong>SECTION 7 - THIRD PARTY LINKS</strong><br> We are not responsible for third‑party websites linked from our store. </p> <p><strong>SECTION 8 - LIABILITY</strong><br> is not liable for damages resulting from the use of this website. </p> <p><strong>SECTION 9 - CONTACT</strong><br> Questions about the Terms of Service should be sent to:<br> </p> <hr> | I47: =SUBSTITUTE(SUBSTITUTE(SUBSTITUTE(SUBSTITUTE(SUBSTITUTE(Templates!$B$5,"{{STORE}}",$A47),"{{EMAIL}}",$B47),"{{DOMAIN}}",IF(C47<>"",C47,IFERROR(MID(B47,FIND("@",B47)+1,255),""))),"{{LAST_UPDATED}}",$E47),"{{ADDRESS_TEXT}}",IF(D47<>"",D47,"[Add mailing address]")) -> <p><strong>Last updated:</strong> March 12, 2041</p> <p> operates this website and collects certain personal information to provide services. </p> <h2>Information We Collect</h2> <ul> <li>Name</li> <li>Email</li> <li>Shipping address</li> <li>Billing address</li> <li>Payment details</li> <li>Device information</li> </ul> <h2>How We Use Information</h2> <ul> <li>Process orders</li> <li>Provide support</li> <li>Improve the store</li> <li>Prevent fraud</li> </ul> <h2>Sharing Information</h2> <p> We may share information with Shopify, payment providers, and shipping partners to fulfill orders. </p> <h2>Cookies</h2> <p> Cookies are used to improve user experience and analyze website traffic. </p> <h2>Your Rights</h2> <p> You may request access, correction, or deletion of your personal information. </p> <h2>Security</h2> <p> We implement security measures to protect your data but cannot guarantee absolute security. </p> <h2>Contact</h2> <p> For privacy questions contact:<br> </p>
E48: March 12, 2042 | F48: =SUBSTITUTE(SUBSTITUTE(Templates!$B$2,"{{STORE}}",$A48),"{{EMAIL}}",$B48) -> <h4 style="text-align: center;">Refund, Replacement &amp; Cancellation Policy</h4> <p>At , each product is made to order and produced specifically for you after the order is placed. Because of this, we maintain a strict but fair refund and replacement policy.</p> <p><strong>1. Order Cancellation</strong></p> <p>Orders may be cancelled <strong>within 6 hours of placing the order.</strong><br>After this period, the order may already be in production and cannot be cancelled or modified.<br>To request a cancellation, please contact us immediately at: </p> <p>Requests submitted after the 6-hour cancellation window cannot be guaranteed as the order may already be in production.</p> <p>If a cancellation request is approved within the allowed time window, a 30% management, processing, and transaction fee will be deducted from the total order value.<br>This fee covers costs that are non-recoverable once the order is placed, including but not limited to:<br>- Payment processing and transaction fees<br>- Order processing and administrative costs<br>- Production preparation and fulfillment system allocation<br>The remaining balance will be refunded to the original payment method.</p> <p><strong>2. Defective, Damaged, or Incorrect Items</strong></p> <p>If you receive an item that is <strong>defective, damaged during shipping, or incorrect</strong>, please contact us within <strong>72 hours after delivery confirmation.</strong><br>Your email must include:<br>- Your order number<br>- <strong>Clear photos</strong> of the product and the issue<br>- A brief description of the problem</p> <p>Please send your request to: </p> <p>After review and approval, we will <strong>either</strong>:<br>- Send a <strong>free replacement</strong>, or<br>- Issue a <strong>full refund</strong></p> <p>We may request additional photos or information to verify the issue.<br>In some cases, we may request the defective item to be returned before processing the resolution.</p> <p><strong>3. Custom &amp; Made-To-Order Products</strong></p> <p>All products sold on are <strong>custom-made or printed on demand.</strong><br>Because these products are made specifically for each order, <strong>we do not accept returns or refunds for the following reasons:</strong><br>- Incorrect size ordered<br>- Change of mind<br>- Incorrect shipping address provided by the customer<br>- Minor color differences due to screen display<br>- Custom name or personalization errors provided by the customer</p> <p>However, we understand mistakes happen. As a courtesy, we may offer <strong>a replacement with a 50% discount</strong> if you wish to reorder the correct size, color, or product.</p> <p><strong>4. Refund Processing</strong></p> <p>If your refund request is approved, refunds will be processed to your <strong>original payment method.</strong><br>Please allow <strong>5–7 business days</strong> for the refund to appear in your account depending on your bank or payment provider.<br>Once a refund has been issued, we will send a <strong>confirmation email.</strong></p> <p><strong>5. Late or Missing Refunds</strong></p> <p>If you have not received your refund:<br>- Check your bank account again.<br>- Contact your credit card company or payment provider.<br>- Contact your bank.</p> <p>Refunds can take several business days to process depending on your financial institution.<br>If 10 business days have passed since the refund confirmation and you still have not received the funds, please contact us at: </p> <p><strong>6. Chargebacks &amp; Payment Disputes</strong></p> <p>If a chargeback or payment dispute is opened without contacting our support team first, we reserve the right to submit all order information, delivery confirmation, and communication records to the payment provider.<br>We are always happy to resolve any issues directly with our customers and encourage contacting us first for the fastest resolution.</p> | G48: =SUBSTITUTE(SUBSTITUTE(Templates!$B$3,"{{STORE}}",$A48),"{{EMAIL}}",$B48) -> <p><strong>Production Time</strong></p> <p>All products at are made-to-order and produced specifically according to your selected design, size, and color. We do not keep inventory, which means each item is manufactured after your order is placed.<br>Production typically takes 5–10 business days (excluding weekends and holidays) before the order is shipped.<br>Orders enter the production process within 6 hours after being placed. Once production has started, orders cannot be modified or canceled.</p> <p><strong>Shipping Time</strong></p> <p>After production is completed, your order will be shipped according to the shipping method selected at checkout.</p> <p>Estimated delivery times:<br>Standard Shipping: 10–20 business days<br>Fast Shipping: 5–10 business days</p> <p>Delivery times may vary depending on your location, customs processing, and carrier delays.<br>Once your order has been shipped, you will receive a tracking number via email.</p> <p><strong>Estimated Delivery Time</strong></p> <p>Total estimated delivery time includes production time + shipping time.<br>Example:<br>- Standard Shipping: 15–30 business days total<br>- Fast Shipping: 10–20 business days total</p> <p>For the most accurate estimate, please check the estimated delivery date on your order confirmation email.<br>If you have any questions about your order, please contact us at: </p> <p><strong>Shipping Cost</strong></p> <p>- $5.95 for orders under $90<br>- Free shipping for orders $90 and above</p> <p><strong> is not responsible for delays caused by carriers, customs clearance, weather conditions, or peak holiday seasons.</strong></p> | H48: =SUBSTITUTE(SUBSTITUTE(SUBSTITUTE(SUBSTITUTE(SUBSTITUTE(Templates!$B$4,"{{STORE}}",$A48),"{{EMAIL}}",$B48),"{{DOMAIN}}",IF(C48<>"",C48,IFERROR(MID(B48,FIND("@",B48)+1,255),""))),"{{LAST_UPDATED}}",$E48),"{{ADDRESS_TEXT}}",IF(D48<>"",D48,"[Add mailing address]")) -> <p><strong>OVERVIEW</strong><br> Welcome to ! The terms “we”, “us” and “our” refer to . operates this store and website, including all related information, content, features, tools, products and services in order to provide you with a shopping experience. is powered by Shopify. </p> <p>By visiting or using our Services, you agree to these Terms of Service.</p> <p><strong>SECTION 1 - ACCESS</strong><br> You must be at least the age of majority in your jurisdiction to use this website. </p> <p><strong>SECTION 2 - PRODUCTS</strong><br> Product colors may appear differently depending on your device display. </p> <p><strong>SECTION 3 - ORDERS</strong><br> We reserve the right to refuse or cancel orders at our discretion. </p> <p><strong>SECTION 4 - PRICES</strong><br> Prices may change without notice. </p> <p><strong>SECTION 5 - SHIPPING</strong><br> Delivery times are estimates only. </p> <p><strong>SECTION 6 - INTELLECTUAL PROPERTY</strong><br> All website content belongs to or its licensors. </p> <p><strong>SECTION 7 - THIRD PARTY LINKS</strong><br> We are not responsible for third‑party websites linked from our store. </p> <p><strong>SECTION 8 - LIABILITY</strong><br> is not liable for damages resulting from the use of this website. </p> <p><strong>SECTION 9 - CONTACT</strong><br> Questions about the Terms of Service should be sent to:<br> </p> <hr> | I48: =SUBSTITUTE(SUBSTITUTE(SUBSTITUTE(SUBSTITUTE(SUBSTITUTE(Templates!$B$5,"{{STORE}}",$A48),"{{EMAIL}}",$B48),"{{DOMAIN}}",IF(C48<>"",C48,IFERROR(MID(B48,FIND("@",B48)+1,255),""))),"{{LAST_UPDATED}}",$E48),"{{ADDRESS_TEXT}}",IF(D48<>"",D48,"[Add mailing address]")) -> <p><strong>Last updated:</strong> March 12, 2042</p> <p> operates this website and collects certain personal information to provide services. </p> <h2>Information We Collect</h2> <ul> <li>Name</li> <li>Email</li> <li>Shipping address</li> <li>Billing address</li> <li>Payment details</li> <li>Device information</li> </ul> <h2>How We Use Information</h2> <ul> <li>Process orders</li> <li>Provide support</li> <li>Improve the store</li> <li>Prevent fraud</li> </ul> <h2>Sharing Information</h2> <p> We may share information with Shopify, payment providers, and shipping partners to fulfill orders. </p> <h2>Cookies</h2> <p> Cookies are used to improve user experience and analyze website traffic. </p> <h2>Your Rights</h2> <p> You may request access, correction, or deletion of your personal information. </p> <h2>Security</h2> <p> We implement security measures to protect your data but cannot guarantee absolute security. </p> <h2>Contact</h2> <p> For privacy questions contact:<br> </p>
E49: March 12, 2043 | F49: =SUBSTITUTE(SUBSTITUTE(Templates!$B$2,"{{STORE}}",$A49),"{{EMAIL}}",$B49) -> <h4 style="text-align: center;">Refund, Replacement &amp; Cancellation Policy</h4> <p>At , each product is made to order and produced specifically for you after the order is placed. Because of this, we maintain a strict but fair refund and replacement policy.</p> <p><strong>1. Order Cancellation</strong></p> <p>Orders may be cancelled <strong>within 6 hours of placing the order.</strong><br>After this period, the order may already be in production and cannot be cancelled or modified.<br>To request a cancellation, please contact us immediately at: </p> <p>Requests submitted after the 6-hour cancellation window cannot be guaranteed as the order may already be in production.</p> <p>If a cancellation request is approved within the allowed time window, a 30% management, processing, and transaction fee will be deducted from the total order value.<br>This fee covers costs that are non-recoverable once the order is placed, including but not limited to:<br>- Payment processing and transaction fees<br>- Order processing and administrative costs<br>- Production preparation and fulfillment system allocation<br>The remaining balance will be refunded to the original payment method.</p> <p><strong>2. Defective, Damaged, or Incorrect Items</strong></p> <p>If you receive an item that is <strong>defective, damaged during shipping, or incorrect</strong>, please contact us within <strong>72 hours after delivery confirmation.</strong><br>Your email must include:<br>- Your order number<br>- <strong>Clear photos</strong> of the product and the issue<br>- A brief description of the problem</p> <p>Please send your request to: </p> <p>After review and approval, we will <strong>either</strong>:<br>- Send a <strong>free replacement</strong>, or<br>- Issue a <strong>full refund</strong></p> <p>We may request additional photos or information to verify the issue.<br>In some cases, we may request the defective item to be returned before processing the resolution.</p> <p><strong>3. Custom &amp; Made-To-Order Products</strong></p> <p>All products sold on are <strong>custom-made or printed on demand.</strong><br>Because these products are made specifically for each order, <strong>we do not accept returns or refunds for the following reasons:</strong><br>- Incorrect size ordered<br>- Change of mind<br>- Incorrect shipping address provided by the customer<br>- Minor color differences due to screen display<br>- Custom name or personalization errors provided by the customer</p> <p>However, we understand mistakes happen. As a courtesy, we may offer <strong>a replacement with a 50% discount</strong> if you wish to reorder the correct size, color, or product.</p> <p><strong>4. Refund Processing</strong></p> <p>If your refund request is approved, refunds will be processed to your <strong>original payment method.</strong><br>Please allow <strong>5–7 business days</strong> for the refund to appear in your account depending on your bank or payment provider.<br>Once a refund has been issued, we will send a <strong>confirmation email.</strong></p> <p><strong>5. Late or Missing Refunds</strong></p> <p>If you have not received your refund:<br>- Check your bank account again.<br>- Contact your credit card company or payment provider.<br>- Contact your bank.</p> <p>Refunds can take several business days to process depending on your financial institution.<br>If 10 business days have passed since the refund confirmation and you still have not received the funds, please contact us at: </p> <p><strong>6. Chargebacks &amp; Payment Disputes</strong></p> <p>If a chargeback or payment dispute is opened without contacting our support team first, we reserve the right to submit all order information, delivery confirmation, and communication records to the payment provider.<br>We are always happy to resolve any issues directly with our customers and encourage contacting us first for the fastest resolution.</p> | G49: =SUBSTITUTE(SUBSTITUTE(Templates!$B$3,"{{STORE}}",$A49),"{{EMAIL}}",$B49) -> <p><strong>Production Time</strong></p> <p>All products at are made-to-order and produced specifically according to your selected design, size, and color. We do not keep inventory, which means each item is manufactured after your order is placed.<br>Production typically takes 5–10 business days (excluding weekends and holidays) before the order is shipped.<br>Orders enter the production process within 6 hours after being placed. Once production has started, orders cannot be modified or canceled.</p> <p><strong>Shipping Time</strong></p> <p>After production is completed, your order will be shipped according to the shipping method selected at checkout.</p> <p>Estimated delivery times:<br>Standard Shipping: 10–20 business days<br>Fast Shipping: 5–10 business days</p> <p>Delivery times may vary depending on your location, customs processing, and carrier delays.<br>Once your order has been shipped, you will receive a tracking number via email.</p> <p><strong>Estimated Delivery Time</strong></p> <p>Total estimated delivery time includes production time + shipping time.<br>Example:<br>- Standard Shipping: 15–30 business days total<br>- Fast Shipping: 10–20 business days total</p> <p>For the most accurate estimate, please check the estimated delivery date on your order confirmation email.<br>If you have any questions about your order, please contact us at: </p> <p><strong>Shipping Cost</strong></p> <p>- $5.95 for orders under $90<br>- Free shipping for orders $90 and above</p> <p><strong> is not responsible for delays caused by carriers, customs clearance, weather conditions, or peak holiday seasons.</strong></p> | H49: =SUBSTITUTE(SUBSTITUTE(SUBSTITUTE(SUBSTITUTE(SUBSTITUTE(Templates!$B$4,"{{STORE}}",$A49),"{{EMAIL}}",$B49),"{{DOMAIN}}",IF(C49<>"",C49,IFERROR(MID(B49,FIND("@",B49)+1,255),""))),"{{LAST_UPDATED}}",$E49),"{{ADDRESS_TEXT}}",IF(D49<>"",D49,"[Add mailing address]")) -> <p><strong>OVERVIEW</strong><br> Welcome to ! The terms “we”, “us” and “our” refer to . operates this store and website, including all related information, content, features, tools, products and services in order to provide you with a shopping experience. is powered by Shopify. </p> <p>By visiting or using our Services, you agree to these Terms of Service.</p> <p><strong>SECTION 1 - ACCESS</strong><br> You must be at least the age of majority in your jurisdiction to use this website. </p> <p><strong>SECTION 2 - PRODUCTS</strong><br> Product colors may appear differently depending on your device display. </p> <p><strong>SECTION 3 - ORDERS</strong><br> We reserve the right to refuse or cancel orders at our discretion. </p> <p><strong>SECTION 4 - PRICES</strong><br> Prices may change without notice. </p> <p><strong>SECTION 5 - SHIPPING</strong><br> Delivery times are estimates only. </p> <p><strong>SECTION 6 - INTELLECTUAL PROPERTY</strong><br> All website content belongs to or its licensors. </p> <p><strong>SECTION 7 - THIRD PARTY LINKS</strong><br> We are not responsible for third‑party websites linked from our store. </p> <p><strong>SECTION 8 - LIABILITY</strong><br> is not liable for damages resulting from the use of this website. </p> <p><strong>SECTION 9 - CONTACT</strong><br> Questions about the Terms of Service should be sent to:<br> </p> <hr> | I49: =SUBSTITUTE(SUBSTITUTE(SUBSTITUTE(SUBSTITUTE(SUBSTITUTE(Templates!$B$5,"{{STORE}}",$A49),"{{EMAIL}}",$B49),"{{DOMAIN}}",IF(C49<>"",C49,IFERROR(MID(B49,FIND("@",B49)+1,255),""))),"{{LAST_UPDATED}}",$E49),"{{ADDRESS_TEXT}}",IF(D49<>"",D49,"[Add mailing address]")) -> <p><strong>Last updated:</strong> March 12, 2043</p> <p> operates this website and collects certain personal information to provide services. </p> <h2>Information We Collect</h2> <ul> <li>Name</li> <li>Email</li> <li>Shipping address</li> <li>Billing address</li> <li>Payment details</li> <li>Device information</li> </ul> <h2>How We Use Information</h2> <ul> <li>Process orders</li> <li>Provide support</li> <li>Improve the store</li> <li>Prevent fraud</li> </ul> <h2>Sharing Information</h2> <p> We may share information with Shopify, payment providers, and shipping partners to fulfill orders. </p> <h2>Cookies</h2> <p> Cookies are used to improve user experience and analyze website traffic. </p> <h2>Your Rights</h2> <p> You may request access, correction, or deletion of your personal information. </p> <h2>Security</h2> <p> We implement security measures to protect your data but cannot guarantee absolute security. </p> <h2>Contact</h2> <p> For privacy questions contact:<br> </p>
